
{"levelNumber":1,"pinkBallPosition":{"x":5.0,"y":0.0},"blueBallPosition":{"x":-5.0,"y":0.0},"hintData":{"position":{"x":0.0,"y":-1.5},"rotation":{"x":0.0,"y":0.0,"z":0.0,"w":1.0},"scale":{"x":1.5,"y":1.0}},"listObstacleData":[{"id":"Obstacle_1","position":{"x":0.0,"y":-6.0},"rotation":{"x":0.0,"y":0.0,"z":0.0,"w":1.0},"scale":{"x":1.0,"y":1.0},"rotateDirection":0,"rotatingSpeed":0.0}]};
{"levelNumber":2,"pinkBallPosition":{"x":5.0,"y":-3.1500000953674318},"blueBallPosition":{"x":-5.0,"y":1.0},"hintData":{"position":{"x":-5.039999961853027,"y":-1.399999976158142},"rotation":{"x":0.0,"y":0.0,"z":0.0,"w":1.0},"scale":{"x":1.0,"y":1.0}},"listObstacleData":[{"id":"Obstacle_1","position":{"x":0.0,"y":-6.0},"rotation":{"x":0.0,"y":0.0,"z":0.0,"w":1.0},"scale":{"x":1.0,"y":1.0},"rotateDirection":0,"rotatingSpeed":0.0}]};
{"levelNumber":3,"pinkBallPosition":{"x":5.0,"y":-3.1500000953674318},"blueBallPosition":{"x":-5.0,"y":-3.1500000953674318},"hintData":{"position":{"x":-6.0,"y":1.0},"rotation":{"x":0.0,"y":0.0,"z":0.0,"w":1.0},"scale":{"x":1.0,"y":1.0}},"listObstacleData":[{"id":"Obstacle_1","position":{"x":0.0,"y":-6.0},"rotation":{"x":0.0,"y":0.0,"z":0.0,"w":1.0},"scale":{"x":1.0,"y":1.0},"rotateDirection":0,"rotatingSpeed":0.0}]};
{"levelNumber":4,"pinkBallPosition":{"x":5.0,"y":2.0},"blueBallPosition":{"x":-5.0,"y":2.0},"hintData":{"position":{"x":-3.0,"y":-0.6000000238418579},"rotation":{"x":0.0,"y":0.0,"z":0.0,"w":1.0},"scale":{"x":1.5,"y":1.2000000476837159}},"listObstacleData":[{"id":"Obstacle_1","position":{"x":0.0,"y":-6.0},"rotation":{"x":0.0,"y":0.0,"z":0.0,"w":1.0},"scale":{"x":1.0,"y":1.0},"rotateDirection":0,"rotatingSpeed":0.0},{"id":"Obstacle_2","position":{"x":0.0,"y":-2.25},"rotation":{"x":0.0,"y":0.0,"z":0.0,"w":1.0},"scale":{"x":1.0,"y":1.0},"rotateDirection":0,"rotatingSpeed":0.0}]};
{"levelNumber":5,"pinkBallPosition":{"x":5.0,"y":-3.1500000953674318},"blueBallPosition":{"x":-5.0,"y":-1.9500000476837159},"hintData":{"position":{"x":-7.0,"y":1.7000000476837159},"rotation":{"x":0.0,"y":0.0,"z":0.0,"w":1.0},"scale":{"x":1.0,"y":1.0}},"listObstacleData":[{"id":"Obstacle_1","position":{"x":0.0,"y":-6.0},"rotation":{"x":0.0,"y":0.0,"z":0.0,"w":1.0},"scale":{"x":1.0,"y":1.0},"rotateDirection":0,"rotatingSpeed":0.0},{"id":"Obstacle_11","position":{"x":-4.0,"y":-3.0},"rotation":{"x":0.0,"y":0.0,"z":0.0,"w":1.0},"scale":{"x":3.0,"y":1.0},"rotateDirection":0,"rotatingSpeed":0.0}]};
{"levelNumber":6,"pinkBallPosition":{"x":2.5,"y":-3.1500000953674318},"blueBallPosition":{"x":-2.5,"y":-3.1500000953674318},"hintData":{"position":{"x":-2.75,"y":1.0},"rotation":{"x":0.0,"y":0.0,"z":0.0,"w":1.0},"scale":{"x":1.0,"y":5.0}},"listObstacleData":[{"id":"Obstacle_3","position":{"x":8.0,"y":-2.75},"rotation":{"x":0.0,"y":0.0,"z":0.0,"w":1.0},"scale":{"x":2.0,"y":1.0},"rotateDirection":0,"rotatingSpeed":0.0},{"id":"Obstacle_1","position":{"x":0.0,"y":-6.0},"rotation":{"x":0.0,"y":0.0,"z":0.0,"w":1.0},"scale":{"x":1.0,"y":1.0},"rotateDirection":0,"rotatingSpeed":0.0},{"id":"Obstacle_3","position":{"x":-8.0,"y":-2.75},"rotation":{"x":0.0,"y":0.0,"z":0.0,"w":1.0},"scale":{"x":2.0,"y":1.0},"rotateDirection":0,"rotatingSpeed":0.0}]};
{"levelNumber":7,"pinkBallPosition":{"x":5.0,"y":-1.7000000476837159},"blueBallPosition":{"x":-5.0,"y":1.7999999523162842},"hintData":{"position":{"x":0.6000000238418579,"y":-1.5},"rotation":{"x":0.0,"y":0.0,"z":0.0,"w":1.0},"scale":{"x":1.25,"y":0.75}},"listObstacleData":[{"id":"Obstacle_1","position":{"x":0.0,"y":-6.0},"rotation":{"x":0.0,"y":0.0,"z":0.0,"w":1.0},"scale":{"x":1.0,"y":1.0},"rotateDirection":0,"rotatingSpeed":0.0},{"id":"Obstacle_4","position":{"x":-5.75,"y":-1.0},"rotation":{"x":0.0,"y":0.0,"z":0.0,"w":1.0},"scale":{"x":3.5,"y":2.5},"rotateDirection":0,"rotatingSpeed":0.0},{"id":"Obstacle_3","position":{"x":7.5,"y":-2.75},"rotation":{"x":0.0,"y":0.0,"z":0.0,"w":1.0},"scale":{"x":2.0,"y":1.0},"rotateDirection":0,"rotatingSpeed":0.0}]};
{"levelNumber":8,"pinkBallPosition":{"x":5.0,"y":-1.0},"blueBallPosition":{"x":-5.0,"y":-3.1500000953674318},"hintData":{"position":{"x":6.400000095367432,"y":2.0},"rotation":{"x":0.0,"y":0.0,"z":0.7071065902709961,"w":-0.7071069478988648},"scale":{"x":1.0,"y":1.0}},"listObstacleData":[{"id":"Obstacle_1","position":{"x":0.0,"y":-6.0},"rotation":{"x":0.0,"y":0.0,"z":0.0,"w":1.0},"scale":{"x":1.0,"y":1.0},"rotateDirection":0,"rotatingSpeed":0.0},{"id":"Obstacle_12","position":{"x":4.0,"y":-2.4000000953674318},"rotation":{"x":0.0,"y":0.0,"z":0.0,"w":1.0},"scale":{"x":3.0,"y":1.5},"rotateDirection":0,"rotatingSpeed":0.0}]};
{"levelNumber":9,"pinkBallPosition":{"x":0.3199999928474426,"y":-3.4000000953674318},"blueBallPosition":{"x":-5.0,"y":2.299999952316284},"hintData":{"position":{"x":-5.71999979019165,"y":4.880000114440918},"rotation":{"x":0.0,"y":0.0,"z":0.0,"w":1.0},"scale":{"x":1.0,"y":1.0}},"listObstacleData":[{"id":"Obstacle_3","position":{"x":2.5,"y":-5.199999809265137},"rotation":{"x":0.0,"y":0.0,"z":0.0,"w":1.0},"scale":{"x":1.0,"y":2.0},"rotateDirection":0,"rotatingSpeed":0.0},{"id":"Obstacle_3","position":{"x":-3.8499999046325685,"y":-1.7999999523162842},"rotation":{"x":0.0,"y":0.0,"z":0.0,"w":1.0},"scale":{"x":1.5,"y":5.0},"rotateDirection":0,"rotatingSpeed":0.0}]};
{"levelNumber":10,"pinkBallPosition":{"x":-5.0,"y":0.5},"blueBallPosition":{"x":5.0,"y":0.5},"hintData":{"position":{"x":0.0,"y":-2.1500000953674318},"rotation":{"x":0.0,"y":0.0,"z":-0.3583679795265198,"w":0.9335803985595703},"scale":{"x":1.5,"y":1.5}},"listObstacleData":[{"id":"Obstacle_1","position":{"x":0.0,"y":-6.0},"rotation":{"x":0.0,"y":0.0,"z":0.0,"w":1.0},"scale":{"x":1.0,"y":1.0},"rotateDirection":0,"rotatingSpeed":0.0},{"id":"Obstacle_3","position":{"x":-5.0,"y":0.0},"rotation":{"x":0.0,"y":0.0,"z":0.0,"w":1.0},"scale":{"x":1.0,"y":0.30000001192092898},"rotateDirection":0,"rotatingSpeed":0.0},{"id":"Obstacle_3","position":{"x":5.0,"y":0.0},"rotation":{"x":0.0,"y":0.0,"z":0.0,"w":1.0},"scale":{"x":1.0,"y":0.30000001192092898},"rotateDirection":0,"rotatingSpeed":0.0}]};
{"levelNumber":11,"pinkBallPosition":{"x":4.0,"y":-0.699999988079071},"blueBallPosition":{"x":-4.0,"y":-0.699999988079071},"hintData":{"position":{"x":0.0,"y":-1.5},"rotation":{"x":0.0,"y":0.0,"z":0.0,"w":1.0},"scale":{"x":1.2000000476837159,"y":1.2000000476837159}},"listObstacleData":[{"id":"Obstacle_3","position":{"x":10.0,"y":-4.0},"rotation":{"x":0.0,"y":0.0,"z":0.0,"w":1.0},"scale":{"x":3.0,"y":3.0},"rotateDirection":0,"rotatingSpeed":0.0},{"id":"Obstacle_3","position":{"x":-10.0,"y":-4.0},"rotation":{"x":0.0,"y":0.0,"z":0.0,"w":1.0},"scale":{"x":3.0,"y":3.0},"rotateDirection":0,"rotatingSpeed":0.0},{"id":"Obstacle_3","position":{"x":11.0,"y":-1.4199999570846558},"rotation":{"x":0.0,"y":0.0,"z":0.0,"w":1.0},"scale":{"x":3.0,"y":0.5},"rotateDirection":0,"rotatingSpeed":0.0},{"id":"Obstacle_3","position":{"x":-11.0,"y":-1.4199999570846558},"rotation":{"x":0.0,"y":0.0,"z":0.0,"w":1.0},"scale":{"x":3.0,"y":0.5},"rotateDirection":0,"rotatingSpeed":0.0}]};
{"levelNumber":12,"pinkBallPosition":{"x":0.0,"y":-3.1500000953674318},"blueBallPosition":{"x":0.0,"y":1.0},"hintData":{"position":{"x":-5.0,"y":-1.350000023841858},"rotation":{"x":0.0,"y":0.0,"z":0.0,"w":1.0},"scale":{"x":1.0,"y":1.0}},"listObstacleData":[{"id":"Obstacle_1","position":{"x":0.0,"y":-6.0},"rotation":{"x":0.0,"y":0.0,"z":0.0,"w":1.0},"scale":{"x":1.0,"y":1.0},"rotateDirection":0,"rotatingSpeed":0.0},{"id":"Obstacle_3","position":{"x":0.0,"y":0.5},"rotation":{"x":0.0,"y":0.0,"z":0.0,"w":1.0},"scale":{"x":1.0,"y":0.30000001192092898},"rotateDirection":0,"rotatingSpeed":0.0}]};
{"levelNumber":13,"pinkBallPosition":{"x":5.0,"y":1.0},"blueBallPosition":{"x":-5.0,"y":1.0},"hintData":{"position":{"x":1.7000000476837159,"y":0.4000000059604645},"rotation":{"x":0.0,"y":0.0,"z":0.0,"w":1.0},"scale":{"x":3.0,"y":2.0}},"listObstacleData":[{"id":"Obstacle_3","position":{"x":7.400000095367432,"y":-3.799999952316284},"rotation":{"x":0.0,"y":0.0,"z":0.0,"w":1.0},"scale":{"x":3.0,"y":5.0},"rotateDirection":0,"rotatingSpeed":0.0}]};
{"levelNumber":14,"pinkBallPosition":{"x":5.0,"y":2.0},"blueBallPosition":{"x":-5.0,"y":2.0},"hintData":{"position":{"x":0.4000000059604645,"y":1.649999976158142},"rotation":{"x":0.0,"y":0.0,"z":0.0,"w":1.0},"scale":{"x":2.5,"y":2.0}},"listObstacleData":[{"id":"Obstacle_1","position":{"x":0.0,"y":-6.0},"rotation":{"x":0.0,"y":0.0,"z":0.0,"w":1.0},"scale":{"x":1.0,"y":1.0},"rotateDirection":0,"rotatingSpeed":0.0},{"id":"Obstacle_2","position":{"x":0.0,"y":-1.3600000143051148},"rotation":{"x":0.0,"y":0.0,"z":0.0,"w":1.0},"scale":{"x":1.5,"y":1.7000000476837159},"rotateDirection":0,"rotatingSpeed":0.0}]};
{"levelNumber":15,"pinkBallPosition":{"x":-5.0,"y":1.0},"blueBallPosition":{"x":5.0,"y":-1.7000000476837159},"hintData":{"position":{"x":0.0,"y":-1.0},"rotation":{"x":0.0,"y":0.0,"z":0.0,"w":1.0},"scale":{"x":2.5,"y":2.5}},"listObstacleData":[{"id":"Obstacle_5","position":{"x":-5.0,"y":0.20000000298023225},"rotation":{"x":0.0,"y":0.0,"z":0.0,"w":1.0},"scale":{"x":2.0,"y":2.0},"rotateDirection":0,"rotatingSpeed":0.0},{"id":"Obstacle_5","position":{"x":5.0,"y":-2.5},"rotation":{"x":0.0,"y":0.0,"z":0.0,"w":1.0},"scale":{"x":2.0,"y":2.0},"rotateDirection":0,"rotatingSpeed":0.0}]};
{"levelNumber":16,"pinkBallPosition":{"x":-1.5,"y":0.15000000596046449},"blueBallPosition":{"x":1.5,"y":0.15000000596046449},"hintData":{"position":{"x":0.0,"y":-0.550000011920929},"rotation":{"x":0.0,"y":0.0,"z":0.0,"w":1.0},"scale":{"x":1.2999999523162842,"y":1.2999999523162842}},"listObstacleData":[{"id":"Obstacle_4","position":{"x":0.0,"y":-0.75},"rotation":{"x":0.0,"y":0.0,"z":0.3826834559440613,"w":0.9238795042037964},"scale":{"x":1.0,"y":1.0},"rotateDirection":0,"rotatingSpeed":0.0}]};
{"levelNumber":17,"pinkBallPosition":{"x":-5.0,"y":3.549999952316284},"blueBallPosition":{"x":5.0,"y":-2.450000047683716},"hintData":{"position":{"x":-0.6000000238418579,"y":-1.600000023841858},"rotation":{"x":0.0,"y":0.0,"z":0.0,"w":1.0},"scale":{"x":1.899999976158142,"y":2.450000047683716}},"listObstacleData":[{"id":"Obstacle_5","position":{"x":-5.0,"y":0.0},"rotation":{"x":0.0,"y":0.0,"z":0.0,"w":1.0},"scale":{"x":1.0,"y":1.0},"rotateDirection":0,"rotatingSpeed":0.0},{"id":"Obstacle_5","position":{"x":-5.0,"y":3.0},"rotation":{"x":0.0,"y":0.0,"z":0.0,"w":1.0},"scale":{"x":1.0,"y":1.0},"rotateDirection":0,"rotatingSpeed":0.0},{"id":"Obstacle_5","position":{"x":-5.0,"y":-3.0},"rotation":{"x":0.0,"y":0.0,"z":0.0,"w":1.0},"scale":{"x":1.0,"y":1.0},"rotateDirection":0,"rotatingSpeed":0.0},{"id":"Obstacle_5","position":{"x":0.0,"y":-3.0},"rotation":{"x":0.0,"y":0.0,"z":0.0,"w":1.0},"scale":{"x":1.0,"y":1.0},"rotateDirection":0,"rotatingSpeed":0.0},{"id":"Obstacle_5","position":{"x":0.0,"y":3.0},"rotation":{"x":0.0,"y":0.0,"z":0.0,"w":1.0},"scale":{"x":1.0,"y":1.0},"rotateDirection":0,"rotatingSpeed":0.0},{"id":"Obstacle_5","position":{"x":0.0,"y":0.0},"rotation":{"x":0.0,"y":0.0,"z":0.0,"w":1.0},"scale":{"x":1.0,"y":1.0},"rotateDirection":0,"rotatingSpeed":0.0},{"id":"Obstacle_5","position":{"x":5.0,"y":0.0},"rotation":{"x":0.0,"y":0.0,"z":0.0,"w":1.0},"scale":{"x":1.0,"y":1.0},"rotateDirection":0,"rotatingSpeed":0.0},{"id":"Obstacle_5","position":{"x":5.0,"y":3.0},"rotation":{"x":0.0,"y":0.0,"z":0.0,"w":1.0},"scale":{"x":1.0,"y":1.0},"rotateDirection":0,"rotatingSpeed":0.0},{"id":"Obstacle_5","position":{"x":5.0,"y":-3.0},"rotation":{"x":0.0,"y":0.0,"z":0.0,"w":1.0},"scale":{"x":1.0,"y":1.0},"rotateDirection":0,"rotatingSpeed":0.0}]};
{"levelNumber":18,"pinkBallPosition":{"x":5.0,"y":-2.450000047683716},"blueBallPosition":{"x":-5.0,"y":3.549999952316284},"hintData":{"position":{"x":0.949999988079071,"y":-0.949999988079071},"rotation":{"x":0.0,"y":0.0,"z":0.0,"w":1.0},"scale":{"x":2.0,"y":2.200000047683716}},"listObstacleData":[{"id":"Obstacle_3","position":{"x":-6.0,"y":2.0},"rotation":{"x":0.0,"y":0.0,"z":0.0,"w":1.0},"scale":{"x":3.0,"y":0.30000001192092898},"rotateDirection":0,"rotatingSpeed":0.0},{"id":"Obstacle_12","position":{"x":4.800000190734863,"y":-4.25},"rotation":{"x":0.0,"y":0.0,"z":0.0,"w":1.0},"scale":{"x":3.0,"y":2.0},"rotateDirection":0,"rotatingSpeed":0.0},{"id":"Obstacle_3","position":{"x":7.0,"y":-1.0},"rotation":{"x":0.0,"y":0.0,"z":0.0,"w":1.0},"scale":{"x":3.0,"y":0.30000001192092898},"rotateDirection":0,"rotatingSpeed":0.0}]};
{"levelNumber":19,"pinkBallPosition":{"x":5.75,"y":1.2999999523162842},"blueBallPosition":{"x":-5.0,"y":1.850000023841858},"hintData":{"position":{"x":-0.6499999761581421,"y":-0.8999999761581421},"rotation":{"x":0.0,"y":0.0,"z":0.0,"w":1.0},"scale":{"x":1.0,"y":1.0}},"listObstacleData":[{"id":"Obstacle_3","position":{"x":-8.300000190734864,"y":-2.200000047683716},"rotation":{"x":0.0,"y":0.0,"z":0.0,"w":1.0},"scale":{"x":2.0,"y":5.0},"rotateDirection":0,"rotatingSpeed":0.0},{"id":"Obstacle_3","position":{"x":5.980000019073486,"y":-6.639999866485596},"rotation":{"x":0.0,"y":0.0,"z":0.0,"w":1.0},"scale":{"x":2.0,"y":5.0},"rotateDirection":0,"rotatingSpeed":0.0},{"id":"Obstacle_3","position":{"x":7.0,"y":-2.4000000953674318},"rotation":{"x":0.0,"y":0.0,"z":0.0,"w":1.0},"scale":{"x":2.0,"y":0.699999988079071},"rotateDirection":0,"rotatingSpeed":0.0},{"id":"Obstacle_3","position":{"x":8.0,"y":-1.399999976158142},"rotation":{"x":0.0,"y":0.0,"z":0.0,"w":1.0},"scale":{"x":2.0,"y":0.699999988079071},"rotateDirection":0,"rotatingSpeed":0.0},{"id":"Obstacle_3","position":{"x":9.0,"y":-0.4000000059604645},"rotation":{"x":0.0,"y":0.0,"z":0.0,"w":1.0},"scale":{"x":2.0,"y":0.699999988079071},"rotateDirection":0,"rotatingSpeed":0.0},{"id":"Obstacle_3","position":{"x":10.0,"y":0.4000000059604645},"rotation":{"x":0.0,"y":0.0,"z":0.0,"w":1.0},"scale":{"x":2.0,"y":0.699999988079071},"rotateDirection":0,"rotatingSpeed":0.0}]};
{"levelNumber":20,"pinkBallPosition":{"x":0.0,"y":-4.199999809265137},"blueBallPosition":{"x":0.0,"y":1.850000023841858},"hintData":{"position":{"x":3.5999999046325685,"y":-2.5},"rotation":{"x":0.0,"y":1.0,"z":0.0,"w":-1.6292068494294654e-7},"scale":{"x":1.0,"y":1.0}},"listObstacleData":[{"id":"Obstacle_3","position":{"x":0.0,"y":-5.25},"rotation":{"x":0.0,"y":0.0,"z":0.0,"w":1.0},"scale":{"x":2.0,"y":1.0},"rotateDirection":0,"rotatingSpeed":0.0},{"id":"Obstacle_3","position":{"x":0.0,"y":1.25},"rotation":{"x":0.0,"y":0.0,"z":0.0,"w":1.0},"scale":{"x":1.0,"y":0.4000000059604645},"rotateDirection":0,"rotatingSpeed":0.0}]};
{"levelNumber":21,"pinkBallPosition":{"x":3.0,"y":-3.1500000953674318},"blueBallPosition":{"x":-3.0,"y":-3.1500000953674318},"hintData":{"position":{"x":-4.0,"y":3.0},"rotation":{"x":0.0,"y":0.0,"z":0.0,"w":1.0},"scale":{"x":1.0,"y":1.0}},"listObstacleData":[{"id":"Obstacle_1","position":{"x":0.0,"y":-6.0},"rotation":{"x":0.0,"y":0.0,"z":0.0,"w":1.0},"scale":{"x":1.0,"y":1.0},"rotateDirection":0,"rotatingSpeed":0.0},{"id":"Obstacle_13","position":{"x":0.0,"y":-4.0},"rotation":{"x":0.0,"y":0.0,"z":0.0,"w":1.0},"scale":{"x":1.0,"y":1.0},"rotateDirection":0,"rotatingSpeed":0.0}]};
{"levelNumber":22,"pinkBallPosition":{"x":3.0,"y":-3.1500000953674318},"blueBallPosition":{"x":-2.5,"y":2.549999952316284},"hintData":{"position":{"x":-4.5,"y":0.30000001192092898},"rotation":{"x":0.0,"y":0.0,"z":0.0,"w":1.0},"scale":{"x":1.100000023841858,"y":1.7000000476837159}},"listObstacleData":[{"id":"Obstacle_1","position":{"x":0.0,"y":-6.0},"rotation":{"x":0.0,"y":0.0,"z":0.0,"w":1.0},"scale":{"x":1.0,"y":1.0},"rotateDirection":0,"rotatingSpeed":0.0},{"id":"Obstacle_5","position":{"x":-2.5,"y":2.0},"rotation":{"x":0.0,"y":0.0,"z":0.0,"w":1.0},"scale":{"x":1.0,"y":1.0},"rotateDirection":0,"rotatingSpeed":0.0},{"id":"Obstacle_13","position":{"x":2.0,"y":0.0},"rotation":{"x":0.0,"y":0.0,"z":0.0,"w":1.0},"scale":{"x":1.0,"y":1.0},"rotateDirection":0,"rotatingSpeed":0.0}]};
{"levelNumber":23,"pinkBallPosition":{"x":4.5,"y":-2.700000047683716},"blueBallPosition":{"x":-2.5,"y":1.0},"hintData":{"position":{"x":0.0,"y":0.30000001192092898},"rotation":{"x":0.0,"y":0.0,"z":0.0,"w":1.0},"scale":{"x":1.2999999523162842,"y":1.2000000476837159}},"listObstacleData":[{"id":"Obstacle_3","position":{"x":-6.0,"y":-4.5},"rotation":{"x":0.0,"y":0.0,"z":0.0,"w":1.0},"scale":{"x":1.5,"y":2.0},"rotateDirection":0,"rotatingSpeed":0.0},{"id":"Obstacle_13","position":{"x":0.0,"y":-5.5},"rotation":{"x":0.0,"y":0.0,"z":0.0,"w":1.0},"scale":{"x":1.0,"y":1.0},"rotateDirection":0,"rotatingSpeed":0.0},{"id":"Obstacle_3","position":{"x":6.0,"y":-4.5},"rotation":{"x":0.0,"y":0.0,"z":0.0,"w":1.0},"scale":{"x":1.5,"y":2.0},"rotateDirection":0,"rotatingSpeed":0.0}]};
{"levelNumber":24,"pinkBallPosition":{"x":0.0,"y":2.549999952316284},"blueBallPosition":{"x":-4.5,"y":-3.0999999046325685},"hintData":{"position":{"x":-4.5,"y":0.6000000238418579},"rotation":{"x":0.0,"y":0.0,"z":0.6819984316825867,"w":0.7313536405563355},"scale":{"x":1.7000000476837159,"y":1.5}},"listObstacleData":[{"id":"Obstacle_1","position":{"x":0.0,"y":-6.0},"rotation":{"x":0.0,"y":0.0,"z":0.0,"w":1.0},"scale":{"x":1.0,"y":1.0},"rotateDirection":0,"rotatingSpeed":0.0},{"id":"Obstacle_13","position":{"x":4.0,"y":0.0},"rotation":{"x":0.0,"y":0.0,"z":0.0,"w":1.0},"scale":{"x":1.0,"y":1.0},"rotateDirection":0,"rotatingSpeed":0.0},{"id":"Obstacle_3","position":{"x":6.0,"y":-1.0},"rotation":{"x":0.0,"y":0.0,"z":0.7071068286895752,"w":0.7071067094802856},"scale":{"x":1.0,"y":1.0},"rotateDirection":0,"rotatingSpeed":0.0},{"id":"Obstacle_5","position":{"x":0.0,"y":2.0},"rotation":{"x":0.0,"y":0.0,"z":0.0,"w":1.0},"scale":{"x":1.0,"y":1.0},"rotateDirection":0,"rotatingSpeed":0.0}]};
{"levelNumber":25,"pinkBallPosition":{"x":5.5,"y":-3.1500000953674318},"blueBallPosition":{"x":-4.5,"y":2.75},"hintData":{"position":{"x":-3.119999885559082,"y":-0.800000011920929},"rotation":{"x":0.0,"y":0.0,"z":0.0,"w":1.0},"scale":{"x":1.399999976158142,"y":1.100000023841858}},"listObstacleData":[{"id":"Obstacle_1","position":{"x":0.0,"y":-6.0},"rotation":{"x":0.0,"y":0.0,"z":0.0,"w":1.0},"scale":{"x":1.0,"y":1.0},"rotateDirection":0,"rotatingSpeed":0.0},{"id":"Obstacle_3","position":{"x":0.0,"y":4.5},"rotation":{"x":0.0,"y":0.0,"z":0.7071068286895752,"w":0.7071067094802856},"scale":{"x":1.0,"y":0.4000000059604645},"rotateDirection":0,"rotatingSpeed":0.0},{"id":"Obstacle_13","position":{"x":5.400000095367432,"y":0.0},"rotation":{"x":0.0,"y":0.0,"z":0.0,"w":1.0},"scale":{"x":1.0,"y":1.0},"rotateDirection":0,"rotatingSpeed":0.0},{"id":"Obstacle_3","position":{"x":0.0,"y":-3.0},"rotation":{"x":0.0,"y":0.0,"z":0.7071068286895752,"w":0.7071067094802856},"scale":{"x":1.0,"y":0.4000000059604645},"rotateDirection":0,"rotatingSpeed":0.0}]};
{"levelNumber":26,"pinkBallPosition":{"x":5.0,"y":0.20000000298023225},"blueBallPosition":{"x":-5.0,"y":0.20000000298023225},"hintData":{"position":{"x":-6.199999809265137,"y":3.5},"rotation":{"x":0.0,"y":0.0,"z":0.0,"w":1.0},"scale":{"x":1.399999976158142,"y":1.100000023841858}},"listObstacleData":[{"id":"Obstacle_3","position":{"x":5.75,"y":-0.5},"rotation":{"x":0.0,"y":0.0,"z":0.0,"w":1.0},"scale":{"x":0.699999988079071,"y":0.5},"rotateDirection":0,"rotatingSpeed":0.0},{"id":"Conveyor_1","position":{"x":0.0,"y":-0.5},"rotation":{"x":0.0,"y":0.0,"z":0.0,"w":1.0},"scale":{"x":1.0,"y":1.0},"rotateDirection":0,"rotatingSpeed":100.0},{"id":"Obstacle_3","position":{"x":-5.75,"y":-0.5},"rotation":{"x":0.0,"y":0.0,"z":0.0,"w":1.0},"scale":{"x":0.699999988079071,"y":0.5},"rotateDirection":0,"rotatingSpeed":0.0}]};
{"levelNumber":27,"pinkBallPosition":{"x":5.28000020980835,"y":-1.440000057220459},"blueBallPosition":{"x":-0.699999988079071,"y":1.2000000476837159},"hintData":{"position":{"x":-1.149999976158142,"y":-0.30000001192092898},"rotation":{"x":0.0,"y":0.0,"z":0.0,"w":1.0},"scale":{"x":1.2000000476837159,"y":1.2000000476837159}},"listObstacleData":[{"id":"Obstacle_3","position":{"x":8.0,"y":-4.0},"rotation":{"x":0.0,"y":0.0,"z":0.0,"w":1.0},"scale":{"x":2.0,"y":3.0},"rotateDirection":0,"rotatingSpeed":0.0},{"id":"Conveyor_3","position":{"x":-0.5,"y":0.5},"rotation":{"x":0.0,"y":0.0,"z":0.0,"w":1.0},"scale":{"x":1.0,"y":1.0},"rotateDirection":1,"rotatingSpeed":200.0}]};
{"levelNumber":28,"pinkBallPosition":{"x":-3.5,"y":-1.7999999523162842},"blueBallPosition":{"x":-5.5,"y":1.5},"hintData":{"position":{"x":0.0,"y":0.0},"rotation":{"x":0.0,"y":0.0,"z":0.0,"w":1.0},"scale":{"x":1.0,"y":1.0}},"listObstacleData":[{"id":"Conveyor_3","position":{"x":-4.5,"y":0.800000011920929},"rotation":{"x":0.0,"y":0.0,"z":0.0,"w":1.0},"scale":{"x":1.0,"y":1.0},"rotateDirection":0,"rotatingSpeed":100.0},{"id":"Conveyor_1","position":{"x":0.0,"y":-2.5},"rotation":{"x":0.0,"y":0.0,"z":0.0,"w":1.0},"scale":{"x":1.0,"y":1.0},"rotateDirection":0,"rotatingSpeed":100.0}]};
{"levelNumber":29,"pinkBallPosition":{"x":3.5,"y":1.100000023841858},"blueBallPosition":{"x":-3.4000000953674318,"y":1.100000023841858},"hintData":{"position":{"x":0.30000001192092898,"y":0.0},"rotation":{"x":0.0,"y":0.0,"z":0.0,"w":1.0},"scale":{"x":2.200000047683716,"y":2.700000047683716}},"listObstacleData":[{"id":"Obstacle_3","position":{"x":3.0,"y":0.4000000059604645},"rotation":{"x":0.0,"y":0.0,"z":0.0,"w":1.0},"scale":{"x":1.0,"y":0.5},"rotateDirection":0,"rotatingSpeed":0.0},{"id":"Conveyor_3","position":{"x":-3.0,"y":0.4000000059604645},"rotation":{"x":0.0,"y":0.0,"z":0.0,"w":1.0},"scale":{"x":1.0,"y":1.0},"rotateDirection":0,"rotatingSpeed":100.0}]};
{"levelNumber":30,"pinkBallPosition":{"x":0.0,"y":-0.5},"blueBallPosition":{"x":0.0,"y":1.5},"hintData":{"position":{"x":0.30000001192092898,"y":0.10000000149011612},"rotation":{"x":0.0,"y":0.0,"z":0.0,"w":1.0},"scale":{"x":1.0499999523162842,"y":1.0}},"listObstacleData":[{"id":"Conveyor_3","position":{"x":0.0,"y":0.800000011920929},"rotation":{"x":0.0,"y":0.0,"z":0.0,"w":1.0},"scale":{"x":1.0,"y":1.0},"rotateDirection":0,"rotatingSpeed":100.0},{"id":"Conveyor_3","position":{"x":0.0,"y":-1.2100000381469727},"rotation":{"x":0.0,"y":0.0,"z":0.0,"w":1.0},"scale":{"x":1.0,"y":1.0},"rotateDirection":0,"rotatingSpeed":100.0}]};
{"levelNumber":31,"pinkBallPosition":{"x":2.5,"y":-3.1500000953674318},"blueBallPosition":{"x":-5.0,"y":0.0},"hintData":{"position":{"x":-5.75,"y":4.0},"rotation":{"x":0.0,"y":0.0,"z":0.0,"w":1.0},"scale":{"x":1.2999999523162842,"y":1.2999999523162842}},"listObstacleData":[{"id":"Wire","position":{"x":1.8200000524520875,"y":-1.340000033378601},"rotation":{"x":0.0,"y":0.0,"z":0.0,"w":1.0},"scale":{"x":1.0,"y":1.0},"rotateDirection":0,"rotatingSpeed":0.0},{"id":"WireDestroyer","position":{"x":-1.399999976158142,"y":-1.0},"rotation":{"x":0.0,"y":0.0,"z":0.0,"w":1.0},"scale":{"x":1.0,"y":1.0},"rotateDirection":0,"rotatingSpeed":0.0},{"id":"Obstacle_1","position":{"x":0.0,"y":-6.0},"rotation":{"x":0.0,"y":0.0,"z":0.0,"w":1.0},"scale":{"x":1.0,"y":1.0},"rotateDirection":0,"rotatingSpeed":0.0},{"id":"Obstacle_3","position":{"x":-6.0,"y":-4.0},"rotation":{"x":0.0,"y":0.0,"z":0.0,"w":1.0},"scale":{"x":2.0,"y":4.0},"rotateDirection":0,"rotatingSpeed":0.0},{"id":"Obstacle_3","position":{"x":10.0,"y":-4.0},"rotation":{"x":0.0,"y":0.0,"z":0.0,"w":1.0},"scale":{"x":2.0,"y":4.0},"rotateDirection":0,"rotatingSpeed":0.0}]};
{"levelNumber":32,"pinkBallPosition":{"x":0.0,"y":-3.799999952316284},"blueBallPosition":{"x":0.3100000023841858,"y":0.8999999761581421},"hintData":{"position":{"x":1.7999999523162842,"y":2.890000104904175},"rotation":{"x":0.0,"y":0.0,"z":0.7123547196388245,"w":-0.701819658279419},"scale":{"x":0.5,"y":0.5}},"listObstacleData":[{"id":"Wire","position":{"x":-0.03999999910593033,"y":-2.450000047683716},"rotation":{"x":0.0,"y":0.0,"z":0.0,"w":1.0},"scale":{"x":1.600000023841858,"y":1.0},"rotateDirection":0,"rotatingSpeed":0.0},{"id":"WireDestroyer","position":{"x":-5.849999904632568,"y":-2.180000066757202},"rotation":{"x":0.0,"y":0.0,"z":0.0,"w":1.0},"scale":{"x":1.0,"y":1.0},"rotateDirection":0,"rotatingSpeed":0.0},{"id":"Obstacle_3","position":{"x":0.23000000417232514,"y":0.27000001072883608},"rotation":{"x":0.0,"y":0.0,"z":0.0,"w":1.0},"scale":{"x":1.5499999523162842,"y":0.4000000059604645},"rotateDirection":0,"rotatingSpeed":0.0},{"id":"Obstacle_3","position":{"x":-7.0,"y":-2.5},"rotation":{"x":0.0,"y":0.0,"z":0.0,"w":1.0},"scale":{"x":1.0,"y":0.4000000059604645},"rotateDirection":0,"rotatingSpeed":0.0},{"id":"Obstacle_3","position":{"x":7.0,"y":-2.5},"rotation":{"x":0.0,"y":0.0,"z":0.0,"w":1.0},"scale":{"x":1.0,"y":0.4000000059604645},"rotateDirection":0,"rotatingSpeed":0.0},{"id":"Obstacle_3","position":{"x":0.23000000417232514,"y":-4.519999980926514},"rotation":{"x":0.0,"y":0.0,"z":0.0,"w":1.0},"scale":{"x":1.0,"y":0.4000000059604645},"rotateDirection":0,"rotatingSpeed":0.0}]};
{"levelNumber":33,"pinkBallPosition":{"x":-5.5,"y":-3.0999999046325685},"blueBallPosition":{"x":-5.5,"y":-0.10000000149011612},"hintData":{"position":{"x":-6.599999904632568,"y":-1.7000000476837159},"rotation":{"x":0.0,"y":0.0,"z":0.0,"w":1.0},"scale":{"x":1.0,"y":1.0}},"listObstacleData":[{"id":"Obstacle_3","position":{"x":-6.800000190734863,"y":-0.699999988079071},"rotation":{"x":0.0,"y":0.0,"z":0.0,"w":1.0},"scale":{"x":2.0,"y":0.4000000059604645},"rotateDirection":0,"rotatingSpeed":0.0},{"id":"Obstacle_3","position":{"x":10.0,"y":-3.5},"rotation":{"x":0.0,"y":0.0,"z":0.0,"w":1.0},"scale":{"x":2.0,"y":4.0},"rotateDirection":0,"rotatingSpeed":0.0},{"id":"WireDestroyer","position":{"x":4.599999904632568,"y":-3.450000047683716},"rotation":{"x":0.0,"y":0.0,"z":0.0,"w":1.0},"scale":{"x":1.0,"y":1.0},"rotateDirection":0,"rotatingSpeed":0.0},{"id":"Wire","position":{"x":1.649999976158142,"y":-0.75},"rotation":{"x":0.0,"y":0.0,"z":0.0,"w":1.0},"scale":{"x":1.2000000476837159,"y":1.0},"rotateDirection":0,"rotatingSpeed":0.0},{"id":"Obstacle_1","position":{"x":0.0,"y":-6.0},"rotation":{"x":0.0,"y":0.0,"z":0.0,"w":1.0},"scale":{"x":1.0,"y":1.0},"rotateDirection":0,"rotatingSpeed":0.0}]};
{"levelNumber":34,"pinkBallPosition":{"x":4.360000133514404,"y":-3.700000047683716},"blueBallPosition":{"x":-5.5,"y":2.0999999046325685},"hintData":{"position":{"x":1.149999976158142,"y":0.699999988079071},"rotation":{"x":0.0,"y":0.0,"z":0.12619899213314057,"w":0.9920049905776978},"scale":{"x":1.100000023841858,"y":1.0}},"listObstacleData":[{"id":"Obstacle_3","position":{"x":-6.800000190734863,"y":1.5},"rotation":{"x":0.0,"y":0.0,"z":0.0,"w":1.0},"scale":{"x":2.0,"y":0.4000000059604645},"rotateDirection":0,"rotatingSpeed":0.0},{"id":"Obstacle_3","position":{"x":8.0,"y":-7.0},"rotation":{"x":0.0,"y":0.0,"z":0.0,"w":1.0},"scale":{"x":2.0,"y":4.0},"rotateDirection":0,"rotatingSpeed":0.0},{"id":"WireDestroyer","position":{"x":4.300000190734863,"y":-0.5},"rotation":{"x":0.0,"y":0.0,"z":0.0,"w":1.0},"scale":{"x":1.0,"y":1.0},"rotateDirection":0,"rotatingSpeed":0.0},{"id":"Wire","position":{"x":-7.0,"y":-0.75},"rotation":{"x":0.0,"y":0.0,"z":0.0,"w":1.0},"scale":{"x":2.5,"y":1.0},"rotateDirection":0,"rotatingSpeed":0.0},{"id":"Obstacle_3","position":{"x":2.1500000953674318,"y":-0.800000011920929},"rotation":{"x":0.0,"y":0.0,"z":0.0,"w":1.0},"scale":{"x":1.0,"y":0.4000000059604645},"rotateDirection":0,"rotatingSpeed":0.0}]};
{"levelNumber":35,"pinkBallPosition":{"x":4.5,"y":1.0},"blueBallPosition":{"x":-3.299999952316284,"y":1.0},"hintData":{"position":{"x":-0.4000000059604645,"y":-0.5},"rotation":{"x":0.0,"y":0.0,"z":0.0,"w":1.0},"scale":{"x":1.5,"y":1.5}},"listObstacleData":[{"id":"Obstacle_1","position":{"x":0.0,"y":-6.0},"rotation":{"x":0.0,"y":0.0,"z":0.0,"w":1.0},"scale":{"x":1.0,"y":1.0},"rotateDirection":0,"rotatingSpeed":0.0},{"id":"WireDestroyer","position":{"x":4.300000190734863,"y":-0.5},"rotation":{"x":0.0,"y":0.0,"z":0.0,"w":1.0},"scale":{"x":1.0,"y":1.0},"rotateDirection":0,"rotatingSpeed":0.0},{"id":"Wire","position":{"x":-3.0,"y":-2.5},"rotation":{"x":0.0,"y":0.0,"z":0.0,"w":1.0},"scale":{"x":2.5,"y":1.0},"rotateDirection":0,"rotatingSpeed":0.0},{"id":"Obstacle_3","position":{"x":4.5,"y":-1.5},"rotation":{"x":0.0,"y":0.0,"z":0.0,"w":1.0},"scale":{"x":0.4000000059604645,"y":3.0},"rotateDirection":0,"rotatingSpeed":0.0}]};
{"levelNumber":36,"pinkBallPosition":{"x":3.5,"y":0.550000011920929},"blueBallPosition":{"x":-3.5,"y":0.550000011920929},"hintData":{"position":{"x":0.0,"y":-0.30000001192092898},"rotation":{"x":0.0,"y":0.0,"z":0.0,"w":1.0},"scale":{"x":2.0999999046325685,"y":1.7000000476837159}},"listObstacleData":[{"id":"Roller_1","position":{"x":0.0,"y":-0.07000000029802323},"rotation":{"x":0.0,"y":0.0,"z":0.0,"w":1.0},"scale":{"x":1.0,"y":1.0},"rotateDirection":0,"rotatingSpeed":0.0},{"id":"Obstacle_3","position":{"x":-3.8499999046325685,"y":0.0},"rotation":{"x":0.0,"y":0.0,"z":0.0,"w":1.0},"scale":{"x":0.5,"y":0.30000001192092898},"rotateDirection":0,"rotatingSpeed":0.0},{"id":"Obstacle_3","position":{"x":3.8499999046325685,"y":0.0},"rotation":{"x":0.0,"y":0.0,"z":0.0,"w":1.0},"scale":{"x":0.5,"y":0.30000001192092898},"rotateDirection":0,"rotatingSpeed":0.0}]};
{"levelNumber":37,"pinkBallPosition":{"x":-1.2000000476837159,"y":-2.25},"blueBallPosition":{"x":-4.5,"y":0.550000011920929},"hintData":{"position":{"x":1.2599999904632569,"y":2.4800000190734865},"rotation":{"x":0.0,"y":0.0,"z":0.0,"w":1.0},"scale":{"x":1.0,"y":1.0}},"listObstacleData":[{"id":"Roller_1","position":{"x":0.0,"y":0.0},"rotation":{"x":0.0,"y":0.0,"z":0.0,"w":1.0},"scale":{"x":1.0,"y":1.0},"rotateDirection":0,"rotatingSpeed":0.0},{"id":"Obstacle_3","position":{"x":-8.5,"y":0.0},"rotation":{"x":0.0,"y":0.0,"z":0.0,"w":1.0},"scale":{"x":2.0,"y":0.30000001192092898},"rotateDirection":0,"rotatingSpeed":0.0},{"id":"Obstacle_3","position":{"x":-0.5,"y":-2.7699999809265138},"rotation":{"x":0.0,"y":0.0,"z":0.0,"w":1.0},"scale":{"x":0.699999988079071,"y":0.30000001192092898},"rotateDirection":0,"rotatingSpeed":0.0}]};
{"levelNumber":38,"pinkBallPosition":{"x":-6.0,"y":-3.5},"blueBallPosition":{"x":-6.0,"y":0.550000011920929},"hintData":{"position":{"x":0.0,"y":-2.299999952316284},"rotation":{"x":0.0,"y":0.0,"z":0.0,"w":1.0},"scale":{"x":1.0,"y":0.6000000238418579}},"listObstacleData":[{"id":"Roller_1","position":{"x":1.2999999523162842,"y":-4.0},"rotation":{"x":0.0,"y":0.0,"z":0.0,"w":1.0},"scale":{"x":1.0,"y":1.0},"rotateDirection":0,"rotatingSpeed":0.0},{"id":"Roller_1","position":{"x":1.2999999523162842,"y":0.0},"rotation":{"x":0.0,"y":0.0,"z":0.0,"w":1.0},"scale":{"x":1.0,"y":1.0},"rotateDirection":0,"rotatingSpeed":0.0},{"id":"Obstacle_3","position":{"x":-6.5,"y":0.0},"rotation":{"x":0.0,"y":0.0,"z":0.0,"w":1.0},"scale":{"x":2.0,"y":0.30000001192092898},"rotateDirection":0,"rotatingSpeed":0.0},{"id":"Obstacle_3","position":{"x":-6.5,"y":-4.0},"rotation":{"x":0.0,"y":0.0,"z":0.0,"w":1.0},"scale":{"x":2.0,"y":0.30000001192092898},"rotateDirection":0,"rotatingSpeed":0.0}]};
{"levelNumber":39,"pinkBallPosition":{"x":5.5,"y":2.25},"blueBallPosition":{"x":-6.0,"y":0.550000011920929},"hintData":{"position":{"x":0.8500000238418579,"y":0.07999999821186066},"rotation":{"x":0.0,"y":0.0,"z":0.0,"w":1.0},"scale":{"x":1.2999999523162842,"y":1.0}},"listObstacleData":[{"id":"Roller_1","position":{"x":1.2999999523162842,"y":0.0},"rotation":{"x":0.0,"y":0.0,"z":0.0,"w":1.0},"scale":{"x":1.0,"y":1.0},"rotateDirection":0,"rotatingSpeed":0.0},{"id":"Obstacle_3","position":{"x":-6.5,"y":0.0},"rotation":{"x":0.0,"y":0.0,"z":0.0,"w":1.0},"scale":{"x":2.0,"y":0.30000001192092898},"rotateDirection":0,"rotatingSpeed":0.0},{"id":"Obstacle_3","position":{"x":8.0,"y":1.7000000476837159},"rotation":{"x":0.0,"y":0.0,"z":0.0,"w":1.0},"scale":{"x":1.5,"y":0.30000001192092898},"rotateDirection":0,"rotatingSpeed":0.0}]};
{"levelNumber":40,"pinkBallPosition":{"x":5.5,"y":0.5},"blueBallPosition":{"x":-5.5,"y":0.5},"hintData":{"position":{"x":0.0,"y":0.10000000149011612},"rotation":{"x":0.0,"y":0.0,"z":1.0,"w":-1.6292068494294654e-7},"scale":{"x":1.600000023841858,"y":1.0}},"listObstacleData":[{"id":"Roller_1","position":{"x":0.0,"y":-1.0},"rotation":{"x":0.0,"y":0.0,"z":0.0,"w":1.0},"scale":{"x":1.0,"y":1.0},"rotateDirection":0,"rotatingSpeed":0.0},{"id":"Obstacle_3","position":{"x":-9.0,"y":0.0},"rotation":{"x":0.0,"y":0.0,"z":0.0,"w":1.0},"scale":{"x":2.0,"y":0.30000001192092898},"rotateDirection":0,"rotatingSpeed":0.0},{"id":"Obstacle_3","position":{"x":9.0,"y":0.009999999776482582},"rotation":{"x":0.0,"y":0.0,"z":0.0,"w":1.0},"scale":{"x":2.0,"y":0.30000001192092898},"rotateDirection":0,"rotatingSpeed":0.0}]};
{"levelNumber":41,"pinkBallPosition":{"x":1.0,"y":-3.4000000953674318},"blueBallPosition":{"x":-1.1200000047683716,"y":4.099999904632568},"hintData":{"position":{"x":-1.7000000476837159,"y":4.699999809265137},"rotation":{"x":0.0,"y":0.0,"z":0.0,"w":1.0},"scale":{"x":2.0,"y":1.5}},"listObstacleData":[{"id":"Obstacle_4","position":{"x":1.0,"y":-1.0},"rotation":{"x":0.0,"y":0.0,"z":0.0,"w":1.0},"scale":{"x":1.0,"y":0.30000001192092898},"rotateDirection":0,"rotatingSpeed":0.0},{"id":"Obstacle_4","position":{"x":1.0,"y":-4.0},"rotation":{"x":0.0,"y":0.0,"z":0.0,"w":1.0},"scale":{"x":1.0,"y":0.30000001192092898},"rotateDirection":0,"rotatingSpeed":0.0},{"id":"Obstacle_4","position":{"x":-1.0,"y":-2.5},"rotation":{"x":0.0,"y":0.0,"z":0.0,"w":1.0},"scale":{"x":1.0,"y":0.30000001192092898},"rotateDirection":0,"rotatingSpeed":0.0},{"id":"Obstacle_4","position":{"x":-1.0,"y":0.5},"rotation":{"x":0.0,"y":0.0,"z":0.0,"w":1.0},"scale":{"x":1.0,"y":0.30000001192092898},"rotateDirection":0,"rotatingSpeed":0.0},{"id":"Obstacle_4","position":{"x":1.0,"y":2.0},"rotation":{"x":0.0,"y":0.0,"z":0.0,"w":1.0},"scale":{"x":1.0,"y":0.30000001192092898},"rotateDirection":0,"rotatingSpeed":0.0},{"id":"Obstacle_4","position":{"x":-1.0,"y":3.5},"rotation":{"x":0.0,"y":0.0,"z":0.0,"w":1.0},"scale":{"x":1.0,"y":0.30000001192092898},"rotateDirection":0,"rotatingSpeed":0.0}]};
{"levelNumber":42,"pinkBallPosition":{"x":0.0,"y":-0.3499999940395355},"blueBallPosition":{"x":0.0,"y":2.6500000953674318},"hintData":{"position":{"x":0.0,"y":0.699999988079071},"rotation":{"x":0.0,"y":0.0,"z":0.0,"w":1.0},"scale":{"x":1.2000000476837159,"y":1.2000000476837159}},"listObstacleData":[{"id":"Obstacle_4","position":{"x":0.0,"y":-1.0},"rotation":{"x":0.0,"y":0.0,"z":0.0,"w":1.0},"scale":{"x":1.0,"y":0.30000001192092898},"rotateDirection":0,"rotatingSpeed":0.0},{"id":"Obstacle_4","position":{"x":0.0,"y":2.0},"rotation":{"x":0.0,"y":0.0,"z":0.0,"w":1.0},"scale":{"x":1.0,"y":0.30000001192092898},"rotateDirection":0,"rotatingSpeed":0.0}]};
{"levelNumber":43,"pinkBallPosition":{"x":5.0,"y":1.2999999523162842},"blueBallPosition":{"x":-5.0,"y":1.3300000429153443},"hintData":{"position":{"x":0.0,"y":-1.0},"rotation":{"x":0.0,"y":0.0,"z":0.0,"w":1.0},"scale":{"x":1.5,"y":1.5}},"listObstacleData":[{"id":"Obstacle_4","position":{"x":0.0,"y":-8.0},"rotation":{"x":0.0,"y":0.0,"z":0.0,"w":1.0},"scale":{"x":1.5,"y":5.0},"rotateDirection":0,"rotatingSpeed":0.0},{"id":"Obstacle_4","position":{"x":-5.0,"y":-4.0},"rotation":{"x":0.0,"y":0.0,"z":0.0,"w":1.0},"scale":{"x":1.0,"y":5.0},"rotateDirection":0,"rotatingSpeed":0.0},{"id":"Obstacle_4","position":{"x":5.0,"y":-4.0},"rotation":{"x":0.0,"y":0.0,"z":0.0,"w":1.0},"scale":{"x":1.0,"y":5.0},"rotateDirection":0,"rotatingSpeed":0.0}]};
{"levelNumber":44,"pinkBallPosition":{"x":0.0,"y":-1.2000000476837159},"blueBallPosition":{"x":0.0,"y":1.5499999523162842},"hintData":{"position":{"x":0.0,"y":0.8999999761581421},"rotation":{"x":0.0,"y":0.0,"z":0.0,"w":1.0},"scale":{"x":1.5,"y":1.5}},"listObstacleData":[{"id":"Obstacle_5","position":{"x":0.0,"y":1.0},"rotation":{"x":0.0,"y":0.0,"z":0.0,"w":1.0},"scale":{"x":2.0,"y":1.0},"rotateDirection":0,"rotatingSpeed":0.0},{"id":"Obstacle_5","position":{"x":0.0,"y":-4.0},"rotation":{"x":0.0,"y":0.0,"z":0.0,"w":1.0},"scale":{"x":2.0,"y":10.0},"rotateDirection":0,"rotatingSpeed":0.0}]};
{"levelNumber":45,"pinkBallPosition":{"x":1.7000000476837159,"y":-3.950000047683716},"blueBallPosition":{"x":-5.300000190734863,"y":-0.4000000059604645},"hintData":{"position":{"x":-0.75,"y":-0.44999998807907107},"rotation":{"x":0.0,"y":0.0,"z":0.0,"w":1.0},"scale":{"x":2.299999952316284,"y":2.0}},"listObstacleData":[{"id":"Obstacle_11","position":{"x":-3.7699999809265138,"y":-1.4500000476837159},"rotation":{"x":0.0,"y":0.0,"z":0.0,"w":1.0},"scale":{"x":2.0,"y":1.0},"rotateDirection":0,"rotatingSpeed":0.0},{"id":"Obstacle_3","position":{"x":-6.300000190734863,"y":-3.299999952316284},"rotation":{"x":0.0,"y":0.0,"z":0.0,"w":1.0},"scale":{"x":3.0,"y":1.5},"rotateDirection":0,"rotatingSpeed":0.0},{"id":"Obstacle_3","position":{"x":-3.5,"y":-5.0},"rotation":{"x":0.0,"y":0.0,"z":0.0,"w":1.0},"scale":{"x":3.0,"y":1.0},"rotateDirection":0,"rotatingSpeed":0.0}]};
{"levelNumber":46,"pinkBallPosition":{"x":3.0,"y":-1.5},"blueBallPosition":{"x":-1.0,"y":1.5},"hintData":{"position":{"x":-2.799999952316284,"y":3.0},"rotation":{"x":0.0,"y":0.0,"z":0.0,"w":1.0},"scale":{"x":1.0,"y":1.0}},"listObstacleData":[{"id":"Obstacle_3","position":{"x":-1.0,"y":1.0},"rotation":{"x":0.0,"y":0.0,"z":0.0,"w":1.0},"scale":{"x":1.0,"y":0.30000001192092898},"rotateDirection":0,"rotatingSpeed":0.0},{"id":"Obstacle_3","position":{"x":2.1500000953674318,"y":-2.0},"rotation":{"x":0.0,"y":0.0,"z":0.0,"w":1.0},"scale":{"x":1.0,"y":0.30000001192092898},"rotateDirection":0,"rotatingSpeed":0.0},{"id":"Obstacle_13","position":{"x":3.5,"y":0.0},"rotation":{"x":0.0,"y":0.0,"z":0.0,"w":1.0},"scale":{"x":1.0,"y":1.0},"rotateDirection":0,"rotatingSpeed":0.0}]};
{"levelNumber":47,"pinkBallPosition":{"x":6.0,"y":-2.6500000953674318},"blueBallPosition":{"x":-5.0,"y":0.0},"hintData":{"position":{"x":-2.0,"y":-2.5999999046325685},"rotation":{"x":0.0,"y":0.0,"z":0.0,"w":1.0},"scale":{"x":1.5,"y":1.5}},"listObstacleData":[{"id":"Obstacle_1","position":{"x":0.0,"y":-7.0},"rotation":{"x":0.0,"y":0.0,"z":0.0,"w":1.0},"scale":{"x":1.0,"y":1.0},"rotateDirection":0,"rotatingSpeed":0.0},{"id":"Obstacle_13","position":{"x":7.0,"y":0.0},"rotation":{"x":0.0,"y":0.0,"z":0.0,"w":1.0},"scale":{"x":1.0,"y":1.0},"rotateDirection":0,"rotatingSpeed":0.0},{"id":"Obstacle_3","position":{"x":7.0,"y":-3.700000047683716},"rotation":{"x":0.0,"y":0.0,"z":0.0,"w":1.0},"scale":{"x":2.0,"y":1.0},"rotateDirection":0,"rotatingSpeed":0.0}]};
{"levelNumber":48,"pinkBallPosition":{"x":5.0,"y":-4.150000095367432},"blueBallPosition":{"x":-4.25,"y":3.0},"hintData":{"position":{"x":-2.119999885559082,"y":-1.4299999475479127},"rotation":{"x":0.0,"y":0.0,"z":0.0,"w":1.0},"scale":{"x":1.2000000476837159,"y":1.2000000476837159}},"listObstacleData":[{"id":"Obstacle_3","position":{"x":1.399999976158142,"y":-4.449999809265137},"rotation":{"x":0.0,"y":0.0,"z":0.0,"w":1.0},"scale":{"x":0.20000000298023225,"y":4.0},"rotateDirection":0,"rotatingSpeed":0.0},{"id":"Obstacle_13","position":{"x":6.0,"y":0.0},"rotation":{"x":0.0,"y":0.0,"z":0.0,"w":1.0},"scale":{"x":1.0,"y":1.0},"rotateDirection":0,"rotatingSpeed":0.0},{"id":"Obstacle_1","position":{"x":0.0,"y":-7.0},"rotation":{"x":0.0,"y":0.0,"z":0.0,"w":1.0},"scale":{"x":1.0,"y":1.0},"rotateDirection":0,"rotatingSpeed":0.0}]};
{"levelNumber":49,"pinkBallPosition":{"x":0.20000000298023225,"y":-2.490000009536743},"blueBallPosition":{"x":-3.0,"y":0.8500000238418579},"hintData":{"position":{"x":-4.0,"y":2.75},"rotation":{"x":0.0,"y":0.0,"z":0.0,"w":1.0},"scale":{"x":1.0,"y":1.0}},"listObstacleData":[{"id":"Obstacle_3","position":{"x":4.329999923706055,"y":-1.5},"rotation":{"x":0.0,"y":0.0,"z":0.7071068286895752,"w":0.7071067094802856},"scale":{"x":0.5,"y":0.30000001192092898},"rotateDirection":0,"rotatingSpeed":0.0},{"id":"Obstacle_3","position":{"x":-0.3400000035762787,"y":-1.5},"rotation":{"x":0.0,"y":0.0,"z":0.7071068286895752,"w":0.7071067094802856},"scale":{"x":0.5,"y":0.30000001192092898},"rotateDirection":0,"rotatingSpeed":0.0},{"id":"Obstacle_3","position":{"x":2.0,"y":-3.0},"rotation":{"x":0.0,"y":0.0,"z":0.0,"w":1.0},"scale":{"x":1.0,"y":0.30000001192092898},"rotateDirection":0,"rotatingSpeed":0.0},{"id":"Obstacle_13","position":{"x":0.0,"y":-5.349999904632568},"rotation":{"x":0.0,"y":0.0,"z":0.0,"w":1.0},"scale":{"x":1.0,"y":1.0},"rotateDirection":0,"rotatingSpeed":0.0},{"id":"Obstacle_3","position":{"x":-3.0,"y":0.3499999940395355},"rotation":{"x":0.0,"y":0.0,"z":0.0,"w":1.0},"scale":{"x":1.0,"y":0.30000001192092898},"rotateDirection":0,"rotatingSpeed":0.0}]};
{"levelNumber":50,"pinkBallPosition":{"x":5.75,"y":0.8500000238418579},"blueBallPosition":{"x":-4.5,"y":0.8500000238418579},"hintData":{"position":{"x":0.800000011920929,"y":2.25},"rotation":{"x":0.0,"y":0.0,"z":0.0,"w":1.0},"scale":{"x":1.5,"y":1.5}},"listObstacleData":[{"id":"Obstacle_3","position":{"x":-4.5,"y":0.3499999940395355},"rotation":{"x":0.0,"y":0.0,"z":0.0,"w":1.0},"scale":{"x":0.5,"y":0.30000001192092898},"rotateDirection":0,"rotatingSpeed":0.0},{"id":"Obstacle_13","position":{"x":1.25,"y":-5.0},"rotation":{"x":0.0,"y":0.0,"z":0.0,"w":1.0},"scale":{"x":1.0,"y":1.0},"rotateDirection":0,"rotatingSpeed":0.0},{"id":"Obstacle_3","position":{"x":-1.0,"y":-1.5},"rotation":{"x":0.0,"y":0.0,"z":0.0,"w":1.0},"scale":{"x":0.5,"y":0.30000001192092898},"rotateDirection":0,"rotatingSpeed":0.0},{"id":"Obstacle_3","position":{"x":3.0,"y":-3.0},"rotation":{"x":0.0,"y":0.0,"z":0.0,"w":1.0},"scale":{"x":0.5,"y":0.30000001192092898},"rotateDirection":0,"rotatingSpeed":0.0},{"id":"Obstacle_3","position":{"x":6.400000095367432,"y":0.3499999940395355},"rotation":{"x":0.0,"y":0.0,"z":0.0,"w":1.0},"scale":{"x":0.5,"y":0.30000001192092898},"rotateDirection":0,"rotatingSpeed":0.0}]};
{"levelNumber":51,"pinkBallPosition":{"x":-4.5,"y":-3.1500000953674318},"blueBallPosition":{"x":-4.5,"y":0.8999999761581421},"hintData":{"position":{"x":5.0,"y":2.5},"rotation":{"x":0.0,"y":1.0,"z":0.0,"w":-1.6292068494294654e-7},"scale":{"x":1.0,"y":1.0}},"listObstacleData":[{"id":"Obstacle_3","position":{"x":-5.5,"y":0.3499999940395355},"rotation":{"x":0.0,"y":0.0,"z":0.0,"w":1.0},"scale":{"x":3.0,"y":0.30000001192092898},"rotateDirection":0,"rotatingSpeed":0.0},{"id":"Obstacle_1","position":{"x":0.0,"y":-6.0},"rotation":{"x":0.0,"y":0.0,"z":0.0,"w":1.0},"scale":{"x":1.0,"y":1.0},"rotateDirection":0,"rotatingSpeed":0.0},{"id":"Obstacle_13","position":{"x":7.300000190734863,"y":-4.550000190734863},"rotation":{"x":0.0,"y":0.0,"z":0.0,"w":1.0},"scale":{"x":1.0,"y":1.0},"rotateDirection":0,"rotatingSpeed":0.0}]};
{"levelNumber":52,"pinkBallPosition":{"x":-2.0,"y":-2.799999952316284},"blueBallPosition":{"x":-4.5,"y":2.0},"hintData":{"position":{"x":-1.600000023841858,"y":2.700000047683716},"rotation":{"x":0.0,"y":0.0,"z":0.0,"w":1.0},"scale":{"x":1.600000023841858,"y":1.2000000476837159}},"listObstacleData":[{"id":"Obstacle_3","position":{"x":-4.5,"y":1.0},"rotation":{"x":0.0,"y":0.0,"z":0.0,"w":1.0},"scale":{"x":1.0,"y":0.30000001192092898},"rotateDirection":0,"rotatingSpeed":0.0},{"id":"Obstacle_13","position":{"x":0.0,"y":-4.300000190734863},"rotation":{"x":0.0,"y":0.0,"z":0.0,"w":1.0},"scale":{"x":1.0,"y":1.0},"rotateDirection":0,"rotatingSpeed":0.0},{"id":"Conveyor_1","position":{"x":0.0,"y":-3.5},"rotation":{"x":0.0,"y":0.0,"z":0.0,"w":1.0},"scale":{"x":1.0,"y":1.0},"rotateDirection":0,"rotatingSpeed":300.0}]};
{"levelNumber":53,"pinkBallPosition":{"x":0.0,"y":-3.700000047683716},"blueBallPosition":{"x":0.0,"y":1.5},"hintData":{"position":{"x":3.799999952316284,"y":-2.0},"rotation":{"x":0.0,"y":1.0,"z":0.0,"w":-1.6292068494294654e-7},"scale":{"x":1.0,"y":1.0}},"listObstacleData":[{"id":"Obstacle_13","position":{"x":0.0,"y":3.75},"rotation":{"x":0.0,"y":0.0,"z":0.0,"w":1.0},"scale":{"x":0.5,"y":0.5},"rotateDirection":0,"rotatingSpeed":0.0},{"id":"Obstacle_3","position":{"x":0.0,"y":-5.5},"rotation":{"x":0.0,"y":0.0,"z":0.0,"w":1.0},"scale":{"x":2.0,"y":2.0},"rotateDirection":0,"rotatingSpeed":0.0},{"id":"Obstacle_3","position":{"x":0.0,"y":1.0},"rotation":{"x":0.0,"y":0.0,"z":0.0,"w":1.0},"scale":{"x":0.30000001192092898,"y":0.30000001192092898},"rotateDirection":0,"rotatingSpeed":0.0}]};
{"levelNumber":54,"pinkBallPosition":{"x":5.5,"y":-3.700000047683716},"blueBallPosition":{"x":-2.0,"y":3.0},"hintData":{"position":{"x":0.550000011920929,"y":1.649999976158142},"rotation":{"x":0.0,"y":0.0,"z":0.0,"w":1.0},"scale":{"x":1.2999999523162842,"y":1.0}},"listObstacleData":[{"id":"Obstacle_3","position":{"x":-4.0,"y":-5.5},"rotation":{"x":0.0,"y":0.0,"z":0.0,"w":1.0},"scale":{"x":0.800000011920929,"y":2.0},"rotateDirection":0,"rotatingSpeed":0.0},{"id":"Obstacle_13","position":{"x":1.0,"y":-5.0},"rotation":{"x":0.0,"y":0.0,"z":0.0,"w":1.0},"scale":{"x":1.0,"y":1.0},"rotateDirection":0,"rotatingSpeed":0.0},{"id":"Obstacle_3","position":{"x":6.0,"y":-5.5},"rotation":{"x":0.0,"y":0.0,"z":0.0,"w":1.0},"scale":{"x":1.0,"y":2.0},"rotateDirection":0,"rotatingSpeed":0.0}]};
{"levelNumber":55,"pinkBallPosition":{"x":5.5,"y":1.2999999523162842},"blueBallPosition":{"x":-5.5,"y":1.2999999523162842},"hintData":{"position":{"x":3.950000047683716,"y":-1.399999976158142},"rotation":{"x":0.0,"y":0.0,"z":0.0,"w":1.0},"scale":{"x":1.0,"y":0.9399999976158142}},"listObstacleData":[{"id":"Obstacle_1","position":{"x":0.0,"y":-6.0},"rotation":{"x":0.0,"y":0.0,"z":0.0,"w":1.0},"scale":{"x":1.0,"y":1.0},"rotateDirection":0,"rotatingSpeed":0.0},{"id":"Obstacle_3","position":{"x":-7.5,"y":-2.0},"rotation":{"x":0.0,"y":0.0,"z":0.0,"w":1.0},"scale":{"x":1.0,"y":4.0},"rotateDirection":0,"rotatingSpeed":0.0},{"id":"Obstacle_3","position":{"x":7.5,"y":-2.0},"rotation":{"x":0.0,"y":0.0,"z":0.0,"w":1.0},"scale":{"x":1.0,"y":4.0},"rotateDirection":0,"rotatingSpeed":0.0},{"id":"Obstacle_13","position":{"x":7.5,"y":6.130000114440918},"rotation":{"x":0.0,"y":0.0,"z":0.0,"w":1.0},"scale":{"x":1.0,"y":1.0},"rotateDirection":0,"rotatingSpeed":0.0},{"id":"Conveyor_1","position":{"x":-1.0,"y":0.6000000238418579},"rotation":{"x":0.0,"y":0.0,"z":0.0,"w":1.0},"scale":{"x":1.0,"y":1.0},"rotateDirection":0,"rotatingSpeed":200.0}]};
{"levelNumber":56,"pinkBallPosition":{"x":4.0,"y":2.5},"blueBallPosition":{"x":-4.0,"y":0.0},"hintData":{"position":{"x":0.30000001192092898,"y":0.20000000298023225},"rotation":{"x":0.0,"y":0.0,"z":0.0,"w":1.0},"scale":{"x":2.0,"y":2.0}},"listObstacleData":[{"id":"Obstacle_3","position":{"x":4.0,"y":2.0},"rotation":{"x":0.0,"y":0.0,"z":0.0,"w":1.0},"scale":{"x":0.30000001192092898,"y":0.30000001192092898},"rotateDirection":0,"rotatingSpeed":0.0},{"id":"Obstacle_3","position":{"x":0.0,"y":0.0},"rotation":{"x":0.0,"y":0.0,"z":0.0,"w":1.0},"scale":{"x":0.30000001192092898,"y":0.30000001192092898},"rotateDirection":0,"rotatingSpeed":0.0},{"id":"Obstacle_3","position":{"x":-4.0,"y":-2.0},"rotation":{"x":0.0,"y":0.0,"z":0.0,"w":1.0},"scale":{"x":0.30000001192092898,"y":0.30000001192092898},"rotateDirection":0,"rotatingSpeed":0.0}]};
{"levelNumber":57,"pinkBallPosition":{"x":-5.0,"y":-2.450000047683716},"blueBallPosition":{"x":-5.0,"y":4.5},"hintData":{"position":{"x":1.399999976158142,"y":-0.550000011920929},"rotation":{"x":0.0,"y":0.0,"z":0.0,"w":1.0},"scale":{"x":1.0,"y":1.0}},"listObstacleData":[{"id":"Obstacle_3","position":{"x":6.0,"y":-2.5},"rotation":{"x":0.0,"y":0.0,"z":0.0,"w":1.0},"scale":{"x":1.0,"y":5.0},"rotateDirection":0,"rotatingSpeed":0.0},{"id":"Obstacle_3","position":{"x":-7.5,"y":-5.0},"rotation":{"x":0.0,"y":0.0,"z":0.0,"w":1.0},"scale":{"x":3.0,"y":3.0},"rotateDirection":0,"rotatingSpeed":0.0},{"id":"Obstacle_3","position":{"x":-7.5,"y":1.0},"rotation":{"x":0.0,"y":0.0,"z":0.0,"w":1.0},"scale":{"x":3.0,"y":0.30000001192092898},"rotateDirection":0,"rotatingSpeed":0.0},{"id":"Obstacle_3","position":{"x":-0.05000000074505806,"y":1.7999999523162842},"rotation":{"x":0.0,"y":0.0,"z":0.7071068286895752,"w":0.7071067094802856},"scale":{"x":0.30000001192092898,"y":0.30000001192092898},"rotateDirection":0,"rotatingSpeed":0.0}]};
{"levelNumber":58,"pinkBallPosition":{"x":6.0,"y":-3.950000047683716},"blueBallPosition":{"x":-6.0,"y":1.0},"hintData":{"position":{"x":-2.5,"y":-1.5},"rotation":{"x":0.0,"y":0.0,"z":0.0,"w":1.0},"scale":{"x":1.7999999523162842,"y":1.0}},"listObstacleData":[{"id":"Obstacle_13","position":{"x":7.5,"y":0.0},"rotation":{"x":0.0,"y":0.0,"z":0.0,"w":1.0},"scale":{"x":1.0,"y":1.0},"rotateDirection":0,"rotatingSpeed":0.0},{"id":"Obstacle_3","position":{"x":-2.680000066757202,"y":-3.2699999809265138},"rotation":{"x":0.0,"y":0.0,"z":0.7071068286895752,"w":0.7071067094802856},"scale":{"x":0.4000000059604645,"y":0.4000000059604645},"rotateDirection":0,"rotatingSpeed":0.0},{"id":"Obstacle_3","position":{"x":2.680000066757202,"y":-3.2699999809265138},"rotation":{"x":0.0,"y":0.0,"z":0.7071068286895752,"w":0.7071067094802856},"scale":{"x":0.4000000059604645,"y":0.4000000059604645},"rotateDirection":0,"rotatingSpeed":0.0},{"id":"Obstacle_3","position":{"x":7.5,"y":-6.5},"rotation":{"x":0.0,"y":0.0,"z":0.0,"w":1.0},"scale":{"x":2.0,"y":3.0},"rotateDirection":0,"rotatingSpeed":0.0},{"id":"Obstacle_3","position":{"x":-7.5,"y":-6.5},"rotation":{"x":0.0,"y":0.0,"z":0.0,"w":1.0},"scale":{"x":2.0,"y":3.0},"rotateDirection":0,"rotatingSpeed":0.0}]};
{"levelNumber":59,"pinkBallPosition":{"x":6.0,"y":-3.950000047683716},"blueBallPosition":{"x":-4.0,"y":-1.5},"hintData":{"position":{"x":-1.2999999523162842,"y":-3.299999952316284},"rotation":{"x":0.0,"y":0.0,"z":0.0,"w":1.0},"scale":{"x":1.399999976158142,"y":2.0}},"listObstacleData":[{"id":"Obstacle_13","position":{"x":7.5,"y":0.0},"rotation":{"x":0.0,"y":0.0,"z":0.0,"w":1.0},"scale":{"x":1.0,"y":1.0},"rotateDirection":0,"rotatingSpeed":0.0},{"id":"Obstacle_3","position":{"x":2.680000066757202,"y":-3.2699999809265138},"rotation":{"x":0.0,"y":0.0,"z":0.7071068286895752,"w":0.7071067094802856},"scale":{"x":0.4000000059604645,"y":0.4000000059604645},"rotateDirection":0,"rotatingSpeed":0.0},{"id":"Obstacle_1","position":{"x":0.0,"y":-6.800000190734863},"rotation":{"x":0.0,"y":0.0,"z":0.0,"w":1.0},"scale":{"x":1.0,"y":1.0},"rotateDirection":0,"rotatingSpeed":0.0}]};
{"levelNumber":60,"pinkBallPosition":{"x":6.0,"y":-3.430000066757202},"blueBallPosition":{"x":-4.5,"y":2.0},"hintData":{"position":{"x":-2.0,"y":-1.7999999523162842},"rotation":{"x":0.0,"y":0.0,"z":0.0,"w":1.0},"scale":{"x":1.5,"y":1.5}},"listObstacleData":[{"id":"Obstacle_13","position":{"x":6.900000095367432,"y":0.0},"rotation":{"x":0.0,"y":0.0,"z":0.0,"w":1.0},"scale":{"x":1.0,"y":1.0},"rotateDirection":0,"rotatingSpeed":0.0},{"id":"Obstacle_3","position":{"x":2.0999999046325685,"y":-4.0},"rotation":{"x":0.0,"y":0.0,"z":0.7071068286895752,"w":0.7071067094802856},"scale":{"x":1.0,"y":0.4000000059604645},"rotateDirection":0,"rotatingSpeed":0.0},{"id":"Obstacle_3","position":{"x":6.800000190734863,"y":-4.5},"rotation":{"x":0.0,"y":0.0,"z":0.0,"w":1.0},"scale":{"x":1.0,"y":1.0},"rotateDirection":0,"rotatingSpeed":0.0},{"id":"Obstacle_3","position":{"x":-6.900000095367432,"y":-4.5},"rotation":{"x":0.0,"y":0.0,"z":0.0,"w":1.0},"scale":{"x":2.0,"y":1.0},"rotateDirection":0,"rotatingSpeed":0.0},{"id":"Obstacle_3","position":{"x":2.0999999046325685,"y":4.0},"rotation":{"x":0.0,"y":0.0,"z":0.7071068286895752,"w":0.7071067094802856},"scale":{"x":1.0,"y":0.4000000059604645},"rotateDirection":0,"rotatingSpeed":0.0}]};
{"levelNumber":61,"pinkBallPosition":{"x":0.0,"y":-2.5},"blueBallPosition":{"x":0.0,"y":2.0},"hintData":{"position":{"x":1.6799999475479127,"y":0.30000001192092898},"rotation":{"x":0.0,"y":0.0,"z":0.0,"w":1.0},"scale":{"x":1.399999976158142,"y":1.2999999523162842}},"listObstacleData":[{"id":"Obstacle_3","position":{"x":0.0,"y":-3.0999999046325685},"rotation":{"x":0.0,"y":0.0,"z":0.0,"w":1.0},"scale":{"x":1.5,"y":0.4000000059604645},"rotateDirection":0,"rotatingSpeed":0.0},{"id":"Obstacle_3","position":{"x":0.0,"y":1.4500000476837159},"rotation":{"x":0.0,"y":0.0,"z":0.0,"w":1.0},"scale":{"x":1.5,"y":0.4000000059604645},"rotateDirection":0,"rotatingSpeed":0.0},{"id":"Obstacle_13","position":{"x":0.0,"y":-0.8299999833106995},"rotation":{"x":0.0,"y":0.0,"z":0.0,"w":1.0},"scale":{"x":0.5,"y":0.5},"rotateDirection":0,"rotatingSpeed":0.0}]};
{"levelNumber":62,"pinkBallPosition":{"x":3.5999999046325685,"y":-1.4500000476837159},"blueBallPosition":{"x":-5.650000095367432,"y":1.75},"hintData":{"position":{"x":-2.5999999046325685,"y":3.200000047683716},"rotation":{"x":0.0,"y":0.0,"z":0.0,"w":1.0},"scale":{"x":1.600000023841858,"y":1.399999976158142}},"listObstacleData":[{"id":"Obstacle_13","position":{"x":6.630000114440918,"y":0.0},"rotation":{"x":0.0,"y":0.0,"z":0.0,"w":1.0},"scale":{"x":1.0,"y":1.0},"rotateDirection":0,"rotatingSpeed":0.0},{"id":"Obstacle_3","position":{"x":5.420000076293945,"y":-1.0},"rotation":{"x":0.0,"y":0.0,"z":0.7071068286895752,"w":0.7071067094802856},"scale":{"x":0.30000001192092898,"y":0.30000001192092898},"rotateDirection":0,"rotatingSpeed":0.0},{"id":"Obstacle_3","position":{"x":1.7799999713897706,"y":-1.0},"rotation":{"x":0.0,"y":0.0,"z":0.7071068286895752,"w":0.7071067094802856},"scale":{"x":0.30000001192092898,"y":0.30000001192092898},"rotateDirection":0,"rotatingSpeed":0.0},{"id":"Obstacle_3","position":{"x":3.5999999046325685,"y":-2.0},"rotation":{"x":0.0,"y":0.0,"z":0.0,"w":1.0},"scale":{"x":0.800000011920929,"y":0.30000001192092898},"rotateDirection":0,"rotatingSpeed":0.0},{"id":"Conveyor_1","position":{"x":-4.0,"y":1.0},"rotation":{"x":0.0,"y":0.0,"z":0.0,"w":1.0},"scale":{"x":1.0,"y":1.0},"rotateDirection":0,"rotatingSpeed":1000.0}]};
{"levelNumber":63,"pinkBallPosition":{"x":2.0,"y":3.0},"blueBallPosition":{"x":-2.0,"y":3.0},"hintData":{"position":{"x":0.0,"y":1.0},"rotation":{"x":0.0,"y":0.0,"z":0.0,"w":1.0},"scale":{"x":1.0,"y":1.0}},"listObstacleData":[{"id":"Obstacle_13","position":{"x":0.0,"y":-5.0},"rotation":{"x":0.0,"y":0.0,"z":0.0,"w":1.0},"scale":{"x":1.0,"y":1.0},"rotateDirection":0,"rotatingSpeed":0.0},{"id":"Obstacle_7","position":{"x":0.0,"y":-3.0},"rotation":{"x":0.0,"y":0.0,"z":0.0,"w":1.0},"scale":{"x":1.0,"y":1.0},"rotateDirection":0,"rotatingSpeed":0.0}]};
{"levelNumber":64,"pinkBallPosition":{"x":5.0,"y":1.5},"blueBallPosition":{"x":-5.0,"y":1.5},"hintData":{"position":{"x":-3.0,"y":1.100000023841858},"rotation":{"x":0.0,"y":0.0,"z":0.8121854662895203,"w":0.5833994150161743},"scale":{"x":1.0,"y":1.0}},"listObstacleData":[{"id":"Obstacle_3","position":{"x":-7.0,"y":-4.5},"rotation":{"x":0.0,"y":0.0,"z":0.0,"w":1.0},"scale":{"x":2.0,"y":4.0},"rotateDirection":0,"rotatingSpeed":0.0},{"id":"Obstacle_3","position":{"x":7.0,"y":-4.5},"rotation":{"x":0.0,"y":0.0,"z":0.0,"w":1.0},"scale":{"x":2.0,"y":4.0},"rotateDirection":0,"rotatingSpeed":0.0},{"id":"Obstacle_12","position":{"x":8.260000228881836,"y":-0.75},"rotation":{"x":0.0,"y":0.0,"z":0.0,"w":1.0},"scale":{"x":2.5,"y":1.0},"rotateDirection":0,"rotatingSpeed":0.0},{"id":"Obstacle_13","position":{"x":0.0,"y":0.550000011920929},"rotation":{"x":0.0,"y":0.0,"z":0.0,"w":1.0},"scale":{"x":-0.36000001430511477,"y":0.4000000059604645},"rotateDirection":0,"rotatingSpeed":0.0}]};
{"levelNumber":65,"pinkBallPosition":{"x":3.5,"y":3.0},"blueBallPosition":{"x":-3.5,"y":3.0},"hintData":{"position":{"x":0.0,"y":-0.800000011920929},"rotation":{"x":0.0,"y":0.0,"z":0.0,"w":1.0},"scale":{"x":1.600000023841858,"y":1.2000000476837159}},"listObstacleData":[{"id":"Obstacle_3","position":{"x":0.0,"y":4.0},"rotation":{"x":0.0,"y":0.0,"z":0.7071068286895752,"w":0.7071067094802856},"scale":{"x":2.0,"y":1.0},"rotateDirection":0,"rotatingSpeed":0.0},{"id":"Obstacle_13","position":{"x":-10.0,"y":0.0},"rotation":{"x":0.0,"y":0.0,"z":0.0,"w":1.0},"scale":{"x":1.0,"y":1.0},"rotateDirection":0,"rotatingSpeed":0.0},{"id":"Obstacle_13","position":{"x":10.0,"y":0.0},"rotation":{"x":0.0,"y":0.0,"z":0.0,"w":1.0},"scale":{"x":1.0,"y":1.0},"rotateDirection":0,"rotatingSpeed":0.0},{"id":"Obstacle_3","position":{"x":4.150000095367432,"y":-1.0},"rotation":{"x":0.0,"y":0.0,"z":0.0,"w":1.0},"scale":{"x":0.30000001192092898,"y":0.30000001192092898},"rotateDirection":0,"rotatingSpeed":0.0},{"id":"Obstacle_3","position":{"x":-4.150000095367432,"y":-1.0},"rotation":{"x":0.0,"y":0.0,"z":0.0,"w":1.0},"scale":{"x":0.30000001192092898,"y":0.30000001192092898},"rotateDirection":0,"rotatingSpeed":0.0}]};
{"levelNumber":66,"pinkBallPosition":{"x":3.5,"y":0.550000011920929},"blueBallPosition":{"x":-3.5,"y":0.550000011920929},"hintData":{"position":{"x":5.0,"y":-1.399999976158142},"rotation":{"x":0.0,"y":0.0,"z":0.0,"w":1.0},"scale":{"x":1.0,"y":1.0}},"listObstacleData":[{"id":"Obstacle_1","position":{"x":0.0,"y":-6.0},"rotation":{"x":0.0,"y":0.0,"z":0.0,"w":1.0},"scale":{"x":1.0,"y":1.0},"rotateDirection":0,"rotatingSpeed":0.0},{"id":"Obstacle_2","position":{"x":0.0,"y":-2.25},"rotation":{"x":0.0,"y":0.0,"z":0.0,"w":1.0},"scale":{"x":1.0,"y":1.0},"rotateDirection":0,"rotatingSpeed":0.0},{"id":"Obstacle_14","position":{"x":0.0,"y":0.0},"rotation":{"x":0.0,"y":0.0,"z":0.0,"w":1.0},"scale":{"x":1.5,"y":1.0},"rotateDirection":0,"rotatingSpeed":0.0}]};
{"levelNumber":67,"pinkBallPosition":{"x":2.75,"y":-3.1500000953674318},"blueBallPosition":{"x":-3.0,"y":-3.1500000953674318},"hintData":{"position":{"x":4.199999809265137,"y":2.0},"rotation":{"x":0.0,"y":0.0,"z":0.0,"w":1.0},"scale":{"x":1.0,"y":1.0}},"listObstacleData":[{"id":"Obstacle_15","position":{"x":3.0,"y":-2.1500000953674318},"rotation":{"x":0.0,"y":0.0,"z":0.0,"w":1.0},"scale":{"x":0.5,"y":0.5},"rotateDirection":0,"rotatingSpeed":0.0},{"id":"Obstacle_1","position":{"x":0.0,"y":-6.0},"rotation":{"x":0.0,"y":0.0,"z":0.0,"w":1.0},"scale":{"x":1.0,"y":1.0},"rotateDirection":0,"rotatingSpeed":0.0}]};
{"levelNumber":68,"pinkBallPosition":{"x":0.0,"y":1.399999976158142},"blueBallPosition":{"x":0.0,"y":2.5999999046325685},"hintData":{"position":{"x":-1.399999976158142,"y":-2.200000047683716},"rotation":{"x":0.0,"y":0.0,"z":0.0,"w":1.0},"scale":{"x":0.5,"y":1.0}},"listObstacleData":[{"id":"Obstacle_1","position":{"x":0.0,"y":-6.0},"rotation":{"x":0.0,"y":0.0,"z":0.0,"w":1.0},"scale":{"x":1.0,"y":1.0},"rotateDirection":0,"rotatingSpeed":0.0},{"id":"Obstacle_16","position":{"x":0.0,"y":2.0},"rotation":{"x":0.0,"y":0.0,"z":0.0,"w":1.0},"scale":{"x":0.5,"y":0.5},"rotateDirection":0,"rotatingSpeed":0.0}]};
{"levelNumber":69,"pinkBallPosition":{"x":1.149999976158142,"y":1.0},"blueBallPosition":{"x":-1.149999976158142,"y":1.0},"hintData":{"position":{"x":-1.5,"y":1.0},"rotation":{"x":0.0,"y":0.0,"z":0.0,"w":1.0},"scale":{"x":1.7000000476837159,"y":1.7000000476837159}},"listObstacleData":[{"id":"Obstacle_17","position":{"x":0.0,"y":0.0},"rotation":{"x":0.0,"y":0.0,"z":0.0,"w":1.0},"scale":{"x":1.0,"y":1.0},"rotateDirection":0,"rotatingSpeed":0.0},{"id":"Obstacle_1","position":{"x":0.0,"y":-6.0},"rotation":{"x":0.0,"y":0.0,"z":0.0,"w":1.0},"scale":{"x":1.0,"y":1.0},"rotateDirection":0,"rotatingSpeed":0.0}]};
{"levelNumber":70,"pinkBallPosition":{"x":4.0,"y":1.5},"blueBallPosition":{"x":-4.0,"y":1.5},"hintData":{"position":{"x":4.800000190734863,"y":-1.2999999523162842},"rotation":{"x":0.0,"y":1.0,"z":0.0,"w":-1.6292068494294654e-7},"scale":{"x":1.0,"y":1.0}},"listObstacleData":[{"id":"Obstacle_18","position":{"x":4.0,"y":1.5},"rotation":{"x":0.0,"y":0.0,"z":0.0,"w":1.0},"scale":{"x":0.5,"y":0.5},"rotateDirection":0,"rotatingSpeed":0.0},{"id":"Obstacle_1","position":{"x":0.0,"y":-6.0},"rotation":{"x":0.0,"y":0.0,"z":0.0,"w":1.0},"scale":{"x":1.0,"y":1.0},"rotateDirection":0,"rotatingSpeed":0.0}]};
{"levelNumber":71,"pinkBallPosition":{"x":3.0,"y":2.5},"blueBallPosition":{"x":-3.0,"y":2.5},"hintData":{"position":{"x":0.30000001192092898,"y":-1.2999999523162842},"rotation":{"x":0.0,"y":1.0,"z":0.0,"w":-1.6292068494294654e-7},"scale":{"x":1.0,"y":1.0}},"listObstacleData":[{"id":"Obstacle_19","position":{"x":0.0,"y":2.5},"rotation":{"x":0.0,"y":0.0,"z":0.0,"w":1.0},"scale":{"x":1.0,"y":1.0},"rotateDirection":0,"rotatingSpeed":0.0},{"id":"Obstacle_1","position":{"x":0.0,"y":-6.0},"rotation":{"x":0.0,"y":0.0,"z":0.0,"w":1.0},"scale":{"x":1.0,"y":1.0},"rotateDirection":0,"rotatingSpeed":0.0}]};
{"levelNumber":72,"pinkBallPosition":{"x":2.0,"y":-2.9000000953674318},"blueBallPosition":{"x":-6.0,"y":-3.1500000953674318},"hintData":{"position":{"x":6.0,"y":-0.8500000238418579},"rotation":{"x":0.0,"y":1.0,"z":0.0,"w":-1.6292068494294654e-7},"scale":{"x":1.0,"y":1.0}},"listObstacleData":[{"id":"Obstacle_1","position":{"x":0.0,"y":-6.0},"rotation":{"x":0.0,"y":0.0,"z":0.0,"w":1.0},"scale":{"x":1.0,"y":1.0},"rotateDirection":0,"rotatingSpeed":0.0},{"id":"Obstacle_20","position":{"x":2.0,"y":-1.649999976158142},"rotation":{"x":0.0,"y":0.0,"z":0.0,"w":1.0},"scale":{"x":0.4000000059604645,"y":0.699999988079071},"rotateDirection":0,"rotatingSpeed":0.0}]};
{"levelNumber":73,"pinkBallPosition":{"x":-1.0,"y":-3.1500000953674318},"blueBallPosition":{"x":-1.0,"y":0.8999999761581421},"hintData":{"position":{"x":-1.399999976158142,"y":1.2999999523162842},"rotation":{"x":0.0,"y":0.0,"z":0.0,"w":1.0},"scale":{"x":1.5,"y":1.5}},"listObstacleData":[{"id":"Obstacle_3","position":{"x":-0.6000000238418579,"y":-2.3499999046325685},"rotation":{"x":0.0,"y":0.0,"z":0.0,"w":1.0},"scale":{"x":0.5,"y":0.20000000298023225},"rotateDirection":0,"rotatingSpeed":0.0},{"id":"Obstacle_3","position":{"x":0.6000000238418579,"y":-0.8999999761581421},"rotation":{"x":0.0,"y":0.0,"z":0.0,"w":1.0},"scale":{"x":0.5,"y":0.20000000298023225},"rotateDirection":0,"rotatingSpeed":0.0},{"id":"Obstacle_3","position":{"x":-0.6000000238418579,"y":0.44999998807907107},"rotation":{"x":0.0,"y":0.0,"z":0.0,"w":1.0},"scale":{"x":0.5,"y":0.20000000298023225},"rotateDirection":0,"rotatingSpeed":0.0},{"id":"Obstacle_3","position":{"x":0.0,"y":1.7000000476837159},"rotation":{"x":0.0,"y":0.0,"z":0.0,"w":1.0},"scale":{"x":0.8399999737739563,"y":0.20000000298023225},"rotateDirection":0,"rotatingSpeed":0.0},{"id":"Obstacle_3","position":{"x":2.0,"y":-1.0},"rotation":{"x":0.0,"y":0.0,"z":0.7071068286895752,"w":0.7071067094802856},"scale":{"x":1.0,"y":0.20000000298023225},"rotateDirection":0,"rotatingSpeed":0.0},{"id":"Obstacle_1","position":{"x":0.0,"y":-6.0},"rotation":{"x":0.0,"y":0.0,"z":0.0,"w":1.0},"scale":{"x":1.0,"y":1.0},"rotateDirection":0,"rotatingSpeed":0.0},{"id":"Obstacle_3","position":{"x":-2.0,"y":-1.0},"rotation":{"x":0.0,"y":0.0,"z":0.7071068286895752,"w":0.7071067094802856},"scale":{"x":1.0,"y":0.20000000298023225},"rotateDirection":0,"rotatingSpeed":0.0}]};
{"levelNumber":74,"pinkBallPosition":{"x":6.0,"y":-3.1500000953674318},"blueBallPosition":{"x":-2.5,"y":3.0},"hintData":{"position":{"x":-3.0,"y":-0.4000000059604645},"rotation":{"x":0.0,"y":0.0,"z":0.0,"w":1.0},"scale":{"x":1.5,"y":1.5}},"listObstacleData":[{"id":"Obstacle_21","position":{"x":-2.5,"y":2.75},"rotation":{"x":0.0,"y":0.0,"z":0.0,"w":1.0},"scale":{"x":0.4000000059604645,"y":0.4000000059604645},"rotateDirection":0,"rotatingSpeed":0.0},{"id":"Obstacle_21","position":{"x":-2.5,"y":3.0},"rotation":{"x":0.0,"y":0.0,"z":0.0,"w":1.0},"scale":{"x":0.5,"y":0.5},"rotateDirection":0,"rotatingSpeed":0.0},{"id":"Obstacle_1","position":{"x":0.0,"y":-6.0},"rotation":{"x":0.0,"y":0.0,"z":0.0,"w":1.0},"scale":{"x":1.0,"y":1.0},"rotateDirection":0,"rotatingSpeed":0.0}]};
{"levelNumber":75,"pinkBallPosition":{"x":0.8999999761581421,"y":-0.699999988079071},"blueBallPosition":{"x":-0.5600000023841858,"y":1.0},"hintData":{"position":{"x":-1.2699999809265137,"y":-0.17000000178813935},"rotation":{"x":0.0,"y":0.0,"z":0.0,"w":1.0},"scale":{"x":1.7000000476837159,"y":2.0}},"listObstacleData":[{"id":"Obstacle_22","position":{"x":0.0,"y":0.0},"rotation":{"x":0.0,"y":0.0,"z":0.0,"w":1.0},"scale":{"x":0.6000000238418579,"y":0.6000000238418579},"rotateDirection":0,"rotatingSpeed":0.0},{"id":"Obstacle_1","position":{"x":0.0,"y":-6.0},"rotation":{"x":0.0,"y":0.0,"z":0.0,"w":1.0},"scale":{"x":1.0,"y":1.0},"rotateDirection":0,"rotatingSpeed":0.0}]};
{"levelNumber":76,"pinkBallPosition":{"x":0.0,"y":-2.0},"blueBallPosition":{"x":-4.0,"y":3.0},"hintData":{"position":{"x":-0.15000000596046449,"y":-0.5},"rotation":{"x":0.0,"y":0.0,"z":0.0,"w":1.0},"scale":{"x":1.7000000476837159,"y":1.399999976158142}},"listObstacleData":[{"id":"Obstacle_3","position":{"x":2.3399999141693117,"y":-0.5},"rotation":{"x":0.0,"y":0.0,"z":0.7071068286895752,"w":0.7071067094802856},"scale":{"x":0.699999988079071,"y":0.30000001192092898},"rotateDirection":0,"rotatingSpeed":0.0},{"id":"Obstacle_3","position":{"x":-2.3399999141693117,"y":-0.5},"rotation":{"x":0.0,"y":0.0,"z":0.7071068286895752,"w":0.7071067094802856},"scale":{"x":0.699999988079071,"y":0.30000001192092898},"rotateDirection":0,"rotatingSpeed":0.0},{"id":"Obstacle_3","position":{"x":0.0,"y":-2.5},"rotation":{"x":0.0,"y":0.0,"z":0.0,"w":1.0},"scale":{"x":1.0,"y":0.30000001192092898},"rotateDirection":0,"rotatingSpeed":0.0}]};
{"levelNumber":77,"pinkBallPosition":{"x":-2.6500000953674318,"y":-1.0},"blueBallPosition":{"x":-5.5,"y":3.0},"hintData":{"position":{"x":-2.1500000953674318,"y":1.3300000429153443},"rotation":{"x":0.0,"y":0.0,"z":0.0,"w":1.0},"scale":{"x":1.7000000476837159,"y":1.399999976158142}},"listObstacleData":[{"id":"Obstacle_3","position":{"x":-1.159999966621399,"y":1.5},"rotation":{"x":0.0,"y":0.0,"z":0.0,"w":1.0},"scale":{"x":1.2000000476837159,"y":0.30000001192092898},"rotateDirection":0,"rotatingSpeed":0.0},{"id":"Obstacle_3","position":{"x":-4.0,"y":0.0},"rotation":{"x":0.0,"y":0.0,"z":0.7071068286895752,"w":0.7071067094802856},"scale":{"x":0.5,"y":0.30000001192092898},"rotateDirection":0,"rotatingSpeed":0.0},{"id":"Obstacle_3","position":{"x":-0.4000000059604645,"y":-1.5},"rotation":{"x":0.0,"y":0.0,"z":0.0,"w":1.0},"scale":{"x":1.5,"y":0.30000001192092898},"rotateDirection":0,"rotatingSpeed":0.0}]};
{"levelNumber":78,"pinkBallPosition":{"x":2.0,"y":1.6799999475479127},"blueBallPosition":{"x":-2.0,"y":1.6799999475479127},"hintData":{"position":{"x":0.17000000178813935,"y":0.949999988079071},"rotation":{"x":0.0,"y":0.0,"z":0.0,"w":1.0},"scale":{"x":2.0,"y":1.399999976158142}},"listObstacleData":[{"id":"Obstacle_3","position":{"x":2.0,"y":1.159999966621399},"rotation":{"x":0.0,"y":0.0,"z":0.0,"w":1.0},"scale":{"x":0.699999988079071,"y":0.30000001192092898},"rotateDirection":0,"rotatingSpeed":0.0},{"id":"Obstacle_3","position":{"x":-2.0,"y":1.159999966621399},"rotation":{"x":0.0,"y":0.0,"z":0.0,"w":1.0},"scale":{"x":0.699999988079071,"y":0.30000001192092898},"rotateDirection":0,"rotatingSpeed":0.0},{"id":"Obstacle_3","position":{"x":0.0,"y":3.5},"rotation":{"x":0.0,"y":0.0,"z":0.7071068286895752,"w":0.7071067094802856},"scale":{"x":1.0,"y":0.30000001192092898},"rotateDirection":0,"rotatingSpeed":0.0}]};
{"levelNumber":79,"pinkBallPosition":{"x":2.0,"y":3.5},"blueBallPosition":{"x":-2.0,"y":3.5},"hintData":{"position":{"x":0.15000000596046449,"y":3.1500000953674318},"rotation":{"x":0.0,"y":0.0,"z":-0.2588190734386444,"w":0.9659258127212524},"scale":{"x":2.0,"y":1.399999976158142}},"listObstacleData":[{"id":"Roller_2","position":{"x":0.0,"y":0.0},"rotation":{"x":0.0,"y":0.0,"z":0.0,"w":1.0},"scale":{"x":1.0,"y":1.0},"rotateDirection":0,"rotatingSpeed":0.0}]};
{"levelNumber":80,"pinkBallPosition":{"x":-2.6500000953674318,"y":-0.5699999928474426},"blueBallPosition":{"x":-5.5,"y":3.0},"hintData":{"position":{"x":-1.0,"y":0.0},"rotation":{"x":0.0,"y":0.0,"z":0.0,"w":1.0},"scale":{"x":2.0,"y":1.5}},"listObstacleData":[{"id":"Obstacle_3","position":{"x":-0.4000000059604645,"y":1.5},"rotation":{"x":0.0,"y":0.0,"z":0.0,"w":1.0},"scale":{"x":1.2999999523162842,"y":0.30000001192092898},"rotateDirection":0,"rotatingSpeed":0.0},{"id":"Obstacle_3","position":{"x":-3.5,"y":0.0},"rotation":{"x":0.0,"y":0.0,"z":0.7071068286895752,"w":0.7071067094802856},"scale":{"x":0.5,"y":0.30000001192092898},"rotateDirection":0,"rotatingSpeed":0.0},{"id":"Obstacle_3","position":{"x":-1.159999966621399,"y":-1.100000023841858},"rotation":{"x":0.0,"y":0.0,"z":0.0,"w":1.0},"scale":{"x":1.0,"y":0.30000001192092898},"rotateDirection":0,"rotatingSpeed":0.0}]};
{"levelNumber":81,"pinkBallPosition":{"x":6.0,"y":3.5},"blueBallPosition":{"x":-6.0,"y":3.5},"hintData":{"position":{"x":0.0,"y":0.5},"rotation":{"x":0.0,"y":0.0,"z":0.0,"w":1.0},"scale":{"x":1.149999976158142,"y":1.2999999523162842}},"listObstacleData":[{"id":"Obstacle_13","position":{"x":10.199999809265137,"y":-3.0},"rotation":{"x":0.0,"y":0.0,"z":0.0,"w":1.0},"scale":{"x":1.0,"y":1.0},"rotateDirection":0,"rotatingSpeed":0.0},{"id":"Obstacle_13","position":{"x":-10.199999809265137,"y":-3.0},"rotation":{"x":0.0,"y":0.0,"z":0.0,"w":1.0},"scale":{"x":1.0,"y":1.0},"rotateDirection":0,"rotatingSpeed":0.0},{"id":"Obstacle_13","position":{"x":0.0,"y":7.150000095367432},"rotation":{"x":0.0,"y":0.0,"z":0.0,"w":1.0},"scale":{"x":1.0,"y":1.0},"rotateDirection":0,"rotatingSpeed":0.0},{"id":"Obstacle_13","position":{"x":0.0,"y":-6.0},"rotation":{"x":0.0,"y":0.0,"z":0.0,"w":1.0},"scale":{"x":1.0,"y":1.0},"rotateDirection":0,"rotatingSpeed":0.0},{"id":"Obstacle_3","position":{"x":0.0,"y":-4.0},"rotation":{"x":0.0,"y":0.0,"z":0.0,"w":1.0},"scale":{"x":0.5,"y":0.30000001192092898},"rotateDirection":0,"rotatingSpeed":0.0},{"id":"Obstacle_3","position":{"x":7.650000095367432,"y":-1.100000023841858},"rotation":{"x":0.0,"y":0.0,"z":0.0,"w":1.0},"scale":{"x":1.0,"y":0.30000001192092898},"rotateDirection":0,"rotatingSpeed":0.0},{"id":"Obstacle_3","position":{"x":-7.650000095367432,"y":-1.100000023841858},"rotation":{"x":0.0,"y":0.0,"z":0.0,"w":1.0},"scale":{"x":1.0,"y":0.30000001192092898},"rotateDirection":0,"rotatingSpeed":0.0}]};
{"levelNumber":82,"pinkBallPosition":{"x":6.0,"y":3.5},"blueBallPosition":{"x":-6.0,"y":3.5},"hintData":{"position":{"x":-1.0,"y":0.6000000238418579},"rotation":{"x":0.0,"y":0.0,"z":0.0,"w":1.0},"scale":{"x":1.2999999523162842,"y":1.0}},"listObstacleData":[{"id":"Conveyor_1","position":{"x":6.0,"y":2.0},"rotation":{"x":0.0,"y":0.0,"z":0.0,"w":1.0},"scale":{"x":1.0,"y":1.0},"rotateDirection":1,"rotatingSpeed":200.0},{"id":"Conveyor_1","position":{"x":-6.0,"y":2.0},"rotation":{"x":0.0,"y":0.0,"z":0.0,"w":1.0},"scale":{"x":1.0,"y":1.0},"rotateDirection":0,"rotatingSpeed":1000.0},{"id":"Obstacle_13","position":{"x":8.0,"y":0.0},"rotation":{"x":0.0,"y":0.0,"z":0.0,"w":1.0},"scale":{"x":1.0,"y":1.0},"rotateDirection":0,"rotatingSpeed":0.0},{"id":"Obstacle_3","position":{"x":8.0,"y":-4.0},"rotation":{"x":0.0,"y":0.0,"z":0.0,"w":1.0},"scale":{"x":2.0,"y":4.0},"rotateDirection":0,"rotatingSpeed":0.0},{"id":"Obstacle_3","position":{"x":-8.5,"y":-4.0},"rotation":{"x":0.0,"y":0.0,"z":0.0,"w":1.0},"scale":{"x":3.0,"y":4.0},"rotateDirection":0,"rotatingSpeed":0.0}]};
{"levelNumber":83,"pinkBallPosition":{"x":6.0,"y":3.5},"blueBallPosition":{"x":-6.0,"y":3.5},"hintData":{"position":{"x":0.0,"y":-2.0},"rotation":{"x":0.0,"y":0.0,"z":0.0,"w":1.0},"scale":{"x":1.2999999523162842,"y":1.0}},"listObstacleData":[{"id":"Conveyor_1","position":{"x":-6.0,"y":0.0},"rotation":{"x":0.0,"y":0.0,"z":0.0,"w":1.0},"scale":{"x":1.0,"y":1.0},"rotateDirection":0,"rotatingSpeed":1000.0},{"id":"Conveyor_1","position":{"x":6.0,"y":0.0},"rotation":{"x":0.0,"y":0.0,"z":0.0,"w":1.0},"scale":{"x":1.0,"y":1.0},"rotateDirection":1,"rotatingSpeed":1000.0},{"id":"Obstacle_3","position":{"x":0.0,"y":0.0},"rotation":{"x":0.0,"y":0.0,"z":0.0,"w":1.0},"scale":{"x":0.5,"y":1.0},"rotateDirection":0,"rotatingSpeed":0.0},{"id":"Obstacle_3","position":{"x":0.0,"y":-4.0},"rotation":{"x":0.0,"y":0.0,"z":0.0,"w":1.0},"scale":{"x":0.5,"y":1.0},"rotateDirection":0,"rotatingSpeed":0.0}]};
{"levelNumber":84,"pinkBallPosition":{"x":-5.0,"y":-2.299999952316284},"blueBallPosition":{"x":-1.5,"y":2.5999999046325685},"hintData":{"position":{"x":3.549999952316284,"y":-2.200000047683716},"rotation":{"x":0.0,"y":0.0,"z":0.0,"w":1.0},"scale":{"x":1.600000023841858,"y":2.2799999713897707}},"listObstacleData":[{"id":"Conveyor_1","position":{"x":0.0,"y":1.899999976158142},"rotation":{"x":0.0,"y":0.0,"z":0.0,"w":1.0},"scale":{"x":1.0,"y":1.0},"rotateDirection":0,"rotatingSpeed":200.0},{"id":"Conveyor_1","position":{"x":-3.5,"y":-3.0},"rotation":{"x":0.0,"y":0.0,"z":0.0,"w":1.0},"scale":{"x":1.0,"y":1.0},"rotateDirection":0,"rotatingSpeed":200.0},{"id":"Conveyor_3","position":{"x":4.5,"y":-1.0},"rotation":{"x":0.0,"y":0.0,"z":0.0,"w":1.0},"scale":{"x":1.0,"y":1.0},"rotateDirection":1,"rotatingSpeed":200.0}]};
{"levelNumber":85,"pinkBallPosition":{"x":-1.5,"y":0.6000000238418579},"blueBallPosition":{"x":-1.5,"y":2.5999999046325685},"hintData":{"position":{"x":4.0,"y":1.0},"rotation":{"x":0.0,"y":0.0,"z":0.0,"w":1.0},"scale":{"x":1.5,"y":1.7999999523162842}},"listObstacleData":[{"id":"Conveyor_1","position":{"x":-1.5,"y":1.899999976158142},"rotation":{"x":0.0,"y":0.0,"z":0.0,"w":1.0},"scale":{"x":1.0,"y":1.0},"rotateDirection":0,"rotatingSpeed":200.0},{"id":"Conveyor_1","position":{"x":-1.5,"y":-0.10000000149011612},"rotation":{"x":0.0,"y":0.0,"z":0.0,"w":1.0},"scale":{"x":1.0,"y":1.0},"rotateDirection":0,"rotatingSpeed":200.0},{"id":"Obstacle_4","position":{"x":4.5,"y":2.0},"rotation":{"x":0.0,"y":0.0,"z":0.0,"w":1.0},"scale":{"x":1.0,"y":1.0},"rotateDirection":0,"rotatingSpeed":0.0}]};
{"levelNumber":86,"pinkBallPosition":{"x":6.0,"y":-3.1500000953674318},"blueBallPosition":{"x":4.0,"y":0.550000011920929},"hintData":{"position":{"x":-0.8999999761581421,"y":-2.9000000953674318},"rotation":{"x":0.0,"y":0.0,"z":0.0,"w":1.0},"scale":{"x":1.0,"y":1.0}},"listObstacleData":[{"id":"Obstacle_1","position":{"x":0.0,"y":-6.0},"rotation":{"x":0.0,"y":0.0,"z":0.0,"w":1.0},"scale":{"x":1.0,"y":1.0},"rotateDirection":0,"rotatingSpeed":0.0},{"id":"Obstacle_3","position":{"x":4.0,"y":0.0},"rotation":{"x":0.0,"y":0.0,"z":0.0,"w":1.0},"scale":{"x":2.0,"y":0.30000001192092898},"rotateDirection":0,"rotatingSpeed":0.0},{"id":"Obstacle_3","position":{"x":-0.8999999761581421,"y":-1.0},"rotation":{"x":0.0,"y":0.0,"z":0.7071068286895752,"w":0.7071067094802856},"scale":{"x":0.30000001192092898,"y":0.30000001192092898},"rotateDirection":0,"rotatingSpeed":0.0},{"id":"Obstacle_3","position":{"x":2.0,"y":-3.0},"rotation":{"x":0.0,"y":0.0,"z":0.7071068286895752,"w":0.7071067094802856},"scale":{"x":0.20000000298023225,"y":0.30000001192092898},"rotateDirection":0,"rotatingSpeed":0.0}]};
{"levelNumber":87,"pinkBallPosition":{"x":2.0,"y":-1.4500000476837159},"blueBallPosition":{"x":-4.0,"y":2.549999952316284},"hintData":{"position":{"x":-4.5,"y":3.5},"rotation":{"x":0.0,"y":0.0,"z":0.0,"w":1.0},"scale":{"x":1.0,"y":1.0}},"listObstacleData":[{"id":"Obstacle_3","position":{"x":-4.0,"y":2.0},"rotation":{"x":0.0,"y":0.0,"z":0.0,"w":1.0},"scale":{"x":0.4000000059604645,"y":0.30000001192092898},"rotateDirection":0,"rotatingSpeed":0.0},{"id":"Obstacle_3","position":{"x":2.5,"y":0.0},"rotation":{"x":0.0,"y":0.0,"z":0.0,"w":1.0},"scale":{"x":0.4000000059604645,"y":0.30000001192092898},"rotateDirection":0,"rotatingSpeed":0.0},{"id":"Conveyor_3","position":{"x":-1.7999999523162842,"y":0.0},"rotation":{"x":0.0,"y":0.0,"z":0.0,"w":1.0},"scale":{"x":1.0,"y":1.0},"rotateDirection":0,"rotatingSpeed":300.0},{"id":"Obstacle_3","position":{"x":2.0,"y":-2.0},"rotation":{"x":0.0,"y":0.0,"z":0.0,"w":1.0},"scale":{"x":0.4000000059604645,"y":0.30000001192092898},"rotateDirection":0,"rotatingSpeed":0.0}]};
{"levelNumber":88,"pinkBallPosition":{"x":-4.0,"y":2.549999952316284},"blueBallPosition":{"x":3.200000047683716,"y":-3.1500000953674318},"hintData":{"position":{"x":-2.0999999046325685,"y":-0.3499999940395355},"rotation":{"x":0.0,"y":0.0,"z":0.0,"w":1.0},"scale":{"x":1.399999976158142,"y":1.2999999523162842}},"listObstacleData":[{"id":"Wire","position":{"x":5.449999809265137,"y":-0.5},"rotation":{"x":0.0,"y":0.0,"z":0.0,"w":1.0},"scale":{"x":1.0,"y":1.0},"rotateDirection":0,"rotatingSpeed":0.0},{"id":"WireDestroyer","position":{"x":2.0,"y":0.05000000074505806},"rotation":{"x":0.0,"y":0.0,"z":0.0,"w":1.0},"scale":{"x":1.0,"y":1.0},"rotateDirection":0,"rotatingSpeed":0.0},{"id":"Obstacle_1","position":{"x":0.0,"y":-6.0},"rotation":{"x":0.0,"y":0.0,"z":0.0,"w":1.0},"scale":{"x":1.0,"y":1.0},"rotateDirection":0,"rotatingSpeed":0.0},{"id":"Obstacle_3","position":{"x":2.0,"y":-1.7000000476837159},"rotation":{"x":0.0,"y":0.0,"z":0.7071068286895752,"w":0.7071067094802856},"scale":{"x":0.699999988079071,"y":1.0},"rotateDirection":0,"rotatingSpeed":0.0}]};
{"levelNumber":89,"pinkBallPosition":{"x":5.0,"y":-1.2000000476837159},"blueBallPosition":{"x":-4.0,"y":3.0},"hintData":{"position":{"x":-1.7000000476837159,"y":0.550000011920929},"rotation":{"x":0.0,"y":0.0,"z":0.0,"w":1.0},"scale":{"x":1.5,"y":1.5}},"listObstacleData":[{"id":"Obstacle_3","position":{"x":-4.5,"y":1.0},"rotation":{"x":0.0,"y":0.0,"z":0.08715575188398361,"w":0.9961947202682495},"scale":{"x":2.0,"y":0.30000001192092898},"rotateDirection":0,"rotatingSpeed":0.0},{"id":"Obstacle_1","position":{"x":0.0,"y":-5.0},"rotation":{"x":0.0,"y":0.0,"z":0.08715575188398361,"w":0.9961947202682495},"scale":{"x":1.0,"y":1.0},"rotateDirection":0,"rotatingSpeed":0.0}]};
{"levelNumber":90,"pinkBallPosition":{"x":5.5,"y":-0.699999988079071},"blueBallPosition":{"x":-5.699999809265137,"y":-0.699999988079071},"hintData":{"position":{"x":0.8999999761581421,"y":-2.200000047683716},"rotation":{"x":0.0,"y":0.0,"z":0.0,"w":1.0},"scale":{"x":1.5,"y":1.0}},"listObstacleData":[{"id":"Obstacle_3","position":{"x":12.5,"y":-4.0},"rotation":{"x":0.0,"y":0.0,"z":0.0,"w":1.0},"scale":{"x":3.0,"y":4.0},"rotateDirection":0,"rotatingSpeed":0.0},{"id":"Obstacle_11","position":{"x":-6.0,"y":-1.7599999904632569},"rotation":{"x":0.0,"y":0.0,"z":0.0,"w":1.0},"scale":{"x":3.0,"y":1.0},"rotateDirection":0,"rotatingSpeed":0.0},{"id":"Obstacle_3","position":{"x":-6.0,"y":-5.5},"rotation":{"x":0.0,"y":0.0,"z":0.0,"w":1.0},"scale":{"x":3.0,"y":4.0},"rotateDirection":0,"rotatingSpeed":0.0}]};
{"levelNumber":91,"pinkBallPosition":{"x":2.799999952316284,"y":-0.699999988079071},"blueBallPosition":{"x":-4.0,"y":2.0},"hintData":{"position":{"x":0.23000000417232514,"y":1.0},"rotation":{"x":0.0,"y":0.0,"z":0.0,"w":1.0},"scale":{"x":2.0,"y":2.0}},"listObstacleData":[{"id":"Obstacle_3","position":{"x":9.0,"y":-4.0},"rotation":{"x":0.0,"y":0.0,"z":0.0,"w":1.0},"scale":{"x":3.0,"y":4.0},"rotateDirection":0,"rotatingSpeed":0.0}]};
{"levelNumber":92,"pinkBallPosition":{"x":1.25,"y":1.2000000476837159},"blueBallPosition":{"x":-1.25,"y":1.2200000286102296},"hintData":{"position":{"x":0.0,"y":1.0},"rotation":{"x":0.0,"y":0.0,"z":0.0,"w":1.0},"scale":{"x":2.299999952316284,"y":2.0}},"listObstacleData":[{"id":"Obstacle_1","position":{"x":0.0,"y":-6.0},"rotation":{"x":0.0,"y":0.0,"z":0.0,"w":1.0},"scale":{"x":1.0,"y":1.0},"rotateDirection":0,"rotatingSpeed":0.0},{"id":"Obstacle_13","position":{"x":0.0,"y":-5.050000190734863},"rotation":{"x":0.0,"y":0.0,"z":0.0,"w":1.0},"scale":{"x":1.0,"y":1.0},"rotateDirection":0,"rotatingSpeed":0.0},{"id":"Conveyor_3","position":{"x":-3.0,"y":0.5},"rotation":{"x":0.0,"y":0.0,"z":0.0,"w":1.0},"scale":{"x":1.0,"y":1.0},"rotateDirection":1,"rotatingSpeed":1000.0},{"id":"Conveyor_3","position":{"x":3.0,"y":0.5},"rotation":{"x":0.0,"y":0.0,"z":0.0,"w":1.0},"scale":{"x":1.0,"y":1.0},"rotateDirection":0,"rotatingSpeed":1000.0}]};
{"levelNumber":93,"pinkBallPosition":{"x":0.0,"y":-0.30000001192092898},"blueBallPosition":{"x":0.0,"y":2.700000047683716},"hintData":{"position":{"x":5.199999809265137,"y":3.0},"rotation":{"x":0.0,"y":1.0,"z":0.0,"w":-1.6292068494294654e-7},"scale":{"x":1.0,"y":1.0}},"listObstacleData":[{"id":"Obstacle_13","position":{"x":-5.5,"y":5.260000228881836},"rotation":{"x":0.0,"y":0.0,"z":0.0,"w":1.0},"scale":{"x":1.0,"y":1.0},"rotateDirection":0,"rotatingSpeed":0.0},{"id":"Conveyor_3","position":{"x":0.0,"y":2.0},"rotation":{"x":0.0,"y":0.0,"z":0.0,"w":1.0},"scale":{"x":1.0,"y":1.0},"rotateDirection":0,"rotatingSpeed":500.0},{"id":"Conveyor_3","position":{"x":0.0,"y":-1.0},"rotation":{"x":0.0,"y":0.0,"z":0.0,"w":1.0},"scale":{"x":1.0,"y":1.0},"rotateDirection":1,"rotatingSpeed":500.0},{"id":"Obstacle_13","position":{"x":5.5,"y":-4.5},"rotation":{"x":0.0,"y":0.0,"z":0.0,"w":1.0},"scale":{"x":1.0,"y":1.0},"rotateDirection":0,"rotatingSpeed":0.0},{"id":"Obstacle_1","position":{"x":0.0,"y":-6.0},"rotation":{"x":0.0,"y":0.0,"z":0.0,"w":1.0},"scale":{"x":1.0,"y":1.0},"rotateDirection":0,"rotatingSpeed":0.0}]};
{"levelNumber":94,"pinkBallPosition":{"x":4.0,"y":0.0},"blueBallPosition":{"x":0.0,"y":1.5},"hintData":{"position":{"x":-0.12999999523162843,"y":0.6700000166893005},"rotation":{"x":0.0,"y":0.0,"z":0.0,"w":1.0},"scale":{"x":2.5,"y":2.0}},"listObstacleData":[{"id":"Obstacle_13","position":{"x":0.0,"y":-1.7999999523162842},"rotation":{"x":0.0,"y":0.0,"z":0.0,"w":1.0},"scale":{"x":0.5,"y":0.5},"rotateDirection":0,"rotatingSpeed":0.0},{"id":"Obstacle_3","position":{"x":0.0,"y":1.0},"rotation":{"x":0.0,"y":0.0,"z":0.0,"w":1.0},"scale":{"x":2.0,"y":0.30000001192092898},"rotateDirection":0,"rotatingSpeed":0.0}]};
{"levelNumber":95,"pinkBallPosition":{"x":4.0,"y":0.0},"blueBallPosition":{"x":0.0,"y":1.5},"hintData":{"position":{"x":0.0,"y":0.6499999761581421},"rotation":{"x":0.0,"y":0.0,"z":0.0,"w":1.0},"scale":{"x":2.5,"y":2.200000047683716}},"listObstacleData":[{"id":"Obstacle_3","position":{"x":-6.0,"y":-2.799999952316284},"rotation":{"x":0.0,"y":0.0,"z":0.0,"w":1.0},"scale":{"x":1.0,"y":0.5},"rotateDirection":0,"rotatingSpeed":0.0},{"id":"Obstacle_13","position":{"x":0.0,"y":-4.25},"rotation":{"x":0.0,"y":0.0,"z":0.0,"w":1.0},"scale":{"x":1.0,"y":1.0},"rotateDirection":0,"rotatingSpeed":0.0},{"id":"Obstacle_3","position":{"x":0.0,"y":1.0},"rotation":{"x":0.0,"y":0.0,"z":0.0,"w":1.0},"scale":{"x":2.0,"y":0.30000001192092898},"rotateDirection":0,"rotatingSpeed":0.0},{"id":"Conveyor_1","position":{"x":3.5,"y":-0.800000011920929},"rotation":{"x":0.0,"y":0.0,"z":0.0,"w":1.0},"scale":{"x":1.0,"y":1.0},"rotateDirection":1,"rotatingSpeed":1000.0}]};
{"levelNumber":96,"pinkBallPosition":{"x":3.0,"y":1.5},"blueBallPosition":{"x":-3.0,"y":1.5},"hintData":{"position":{"x":6.0,"y":0.0},"rotation":{"x":0.0,"y":0.0,"z":0.0,"w":1.0},"scale":{"x":0.800000011920929,"y":0.800000011920929}},"listObstacleData":[{"id":"Obstacle_3","position":{"x":-3.0,"y":1.0},"rotation":{"x":0.0,"y":0.0,"z":0.0,"w":1.0},"scale":{"x":0.6000000238418579,"y":0.30000001192092898},"rotateDirection":0,"rotatingSpeed":0.0},{"id":"Obstacle_13","position":{"x":-3.0,"y":2.75},"rotation":{"x":0.0,"y":0.0,"z":0.0,"w":1.0},"scale":{"x":0.30000001192092898,"y":0.30000001192092898},"rotateDirection":0,"rotatingSpeed":0.0},{"id":"Obstacle_3","position":{"x":-6.0,"y":-4.0},"rotation":{"x":0.0,"y":0.0,"z":0.0,"w":1.0},"scale":{"x":1.5,"y":3.0},"rotateDirection":0,"rotatingSpeed":0.0},{"id":"Obstacle_3","position":{"x":3.0,"y":1.0},"rotation":{"x":0.0,"y":0.0,"z":0.0,"w":1.0},"scale":{"x":0.6000000238418579,"y":0.30000001192092898},"rotateDirection":0,"rotatingSpeed":0.0},{"id":"Obstacle_13","position":{"x":3.0,"y":2.75},"rotation":{"x":0.0,"y":0.0,"z":0.0,"w":1.0},"scale":{"x":0.30000001192092898,"y":0.30000001192092898},"rotateDirection":0,"rotatingSpeed":0.0},{"id":"Obstacle_3","position":{"x":6.0,"y":-4.0},"rotation":{"x":0.0,"y":0.0,"z":0.0,"w":1.0},"scale":{"x":1.5,"y":3.0},"rotateDirection":0,"rotatingSpeed":0.0}]};
{"levelNumber":97,"pinkBallPosition":{"x":0.0,"y":2.549999952316284},"blueBallPosition":{"x":3.0,"y":-3.6500000953674318},"hintData":{"position":{"x":2.5,"y":0.20000000298023225},"rotation":{"x":0.0,"y":0.0,"z":0.0,"w":1.0},"scale":{"x":1.5,"y":1.5}},"listObstacleData":[{"id":"WireDestroyer","position":{"x":-6.0,"y":-1.7999999523162842},"rotation":{"x":0.0,"y":0.0,"z":0.0,"w":1.0},"scale":{"x":1.0,"y":1.0},"rotateDirection":0,"rotatingSpeed":0.0},{"id":"Wire","position":{"x":0.0,"y":-2.0},"rotation":{"x":0.0,"y":0.0,"z":0.0,"w":1.0},"scale":{"x":1.0,"y":1.0},"rotateDirection":0,"rotatingSpeed":0.0},{"id":"Obstacle_3","position":{"x":8.0,"y":-2.0},"rotation":{"x":0.0,"y":0.0,"z":0.0,"w":1.0},"scale":{"x":2.0,"y":0.30000001192092898},"rotateDirection":0,"rotatingSpeed":0.0},{"id":"Obstacle_1","position":{"x":0.0,"y":-6.5},"rotation":{"x":0.0,"y":0.0,"z":0.0,"w":1.0},"scale":{"x":1.0,"y":1.0},"rotateDirection":0,"rotatingSpeed":0.0},{"id":"Obstacle_3","position":{"x":-8.0,"y":-2.0},"rotation":{"x":0.0,"y":0.0,"z":0.0,"w":1.0},"scale":{"x":2.0,"y":0.30000001192092898},"rotateDirection":0,"rotatingSpeed":0.0},{"id":"Obstacle_3","position":{"x":-4.5,"y":2.0},"rotation":{"x":0.0,"y":0.0,"z":0.0,"w":1.0},"scale":{"x":3.0,"y":0.30000001192092898},"rotateDirection":0,"rotatingSpeed":0.0}]};
{"levelNumber":98,"pinkBallPosition":{"x":-5.75,"y":1.5499999523162842},"blueBallPosition":{"x":5.75,"y":1.5499999523162842},"hintData":{"position":{"x":2.700000047683716,"y":1.350000023841858},"rotation":{"x":0.0,"y":0.0,"z":0.0,"w":1.0},"scale":{"x":1.0,"y":1.0}},"listObstacleData":[{"id":"Wire","position":{"x":-2.8499999046325685,"y":1.0},"rotation":{"x":0.0,"y":0.0,"z":0.0,"w":1.0},"scale":{"x":0.5,"y":1.0},"rotateDirection":0,"rotatingSpeed":0.0},{"id":"Obstacle_3","position":{"x":7.0,"y":1.0},"rotation":{"x":0.0,"y":0.0,"z":0.0,"w":1.0},"scale":{"x":1.0,"y":0.30000001192092898},"rotateDirection":0,"rotatingSpeed":0.0},{"id":"Obstacle_3","position":{"x":0.0,"y":1.0},"rotation":{"x":0.0,"y":0.0,"z":0.0,"w":1.0},"scale":{"x":0.5,"y":0.30000001192092898},"rotateDirection":0,"rotatingSpeed":0.0},{"id":"Obstacle_3","position":{"x":0.0,"y":-5.0},"rotation":{"x":0.0,"y":0.0,"z":0.0,"w":1.0},"scale":{"x":0.5,"y":2.0},"rotateDirection":0,"rotatingSpeed":0.0},{"id":"Obstacle_3","position":{"x":-9.0,"y":-5.0},"rotation":{"x":0.0,"y":0.0,"z":0.0,"w":1.0},"scale":{"x":2.0,"y":2.0},"rotateDirection":0,"rotatingSpeed":0.0},{"id":"WireDestroyer","position":{"x":0.0,"y":1.2000000476837159},"rotation":{"x":0.0,"y":0.0,"z":0.0,"w":1.0},"scale":{"x":1.0,"y":1.0},"rotateDirection":0,"rotatingSpeed":0.0},{"id":"Wire","position":{"x":2.8499999046325685,"y":1.0},"rotation":{"x":0.0,"y":0.0,"z":0.0,"w":1.0},"scale":{"x":0.5,"y":1.0},"rotateDirection":0,"rotatingSpeed":0.0},{"id":"Obstacle_3","position":{"x":9.0,"y":-5.0},"rotation":{"x":0.0,"y":0.0,"z":0.0,"w":1.0},"scale":{"x":2.0,"y":2.0},"rotateDirection":0,"rotatingSpeed":0.0},{"id":"Obstacle_3","position":{"x":-7.0,"y":1.0},"rotation":{"x":0.0,"y":0.0,"z":0.0,"w":1.0},"scale":{"x":1.0,"y":0.30000001192092898},"rotateDirection":0,"rotatingSpeed":0.0}]};
{"levelNumber":99,"pinkBallPosition":{"x":0.0,"y":0.550000011920929},"blueBallPosition":{"x":0.0,"y":-1.5},"hintData":{"position":{"x":1.399999976158142,"y":-1.5},"rotation":{"x":0.0,"y":0.0,"z":0.0,"w":1.0},"scale":{"x":1.100000023841858,"y":1.149999976158142}},"listObstacleData":[{"id":"Obstacle_3","position":{"x":0.0,"y":-3.0},"rotation":{"x":0.0,"y":0.0,"z":0.0,"w":1.0},"scale":{"x":0.5,"y":0.30000001192092898},"rotateDirection":0,"rotatingSpeed":0.0},{"id":"Obstacle_3","position":{"x":-1.0499999523162842,"y":-1.5},"rotation":{"x":0.0,"y":0.0,"z":0.7071068286895752,"w":0.7071067094802856},"scale":{"x":0.5,"y":0.30000001192092898},"rotateDirection":0,"rotatingSpeed":0.0},{"id":"Obstacle_3","position":{"x":0.0,"y":0.0},"rotation":{"x":0.0,"y":0.0,"z":0.0,"w":1.0},"scale":{"x":0.5,"y":0.30000001192092898},"rotateDirection":0,"rotatingSpeed":0.0}]};
{"levelNumber":100,"pinkBallPosition":{"x":0.5,"y":0.30000001192092898},"blueBallPosition":{"x":-0.5,"y":0.30000001192092898},"hintData":{"position":{"x":0.0,"y":-0.8600000143051148},"rotation":{"x":0.0,"y":0.0,"z":0.0,"w":1.0},"scale":{"x":1.0,"y":1.0}},"listObstacleData":[{"id":"Obstacle_16","position":{"x":0.0,"y":0.5},"rotation":{"x":0.0,"y":0.0,"z":0.7071065902709961,"w":-0.7071069478988648},"scale":{"x":0.6000000238418579,"y":0.6000000238418579},"rotateDirection":0,"rotatingSpeed":0.0},{"id":"Obstacle_1","position":{"x":0.0,"y":-6.0},"rotation":{"x":0.0,"y":0.0,"z":0.0,"w":1.0},"scale":{"x":1.0,"y":1.0},"rotateDirection":0,"rotatingSpeed":0.0}]}